Workbook
Name NativeTimeline_Application_Date: #N/A
Name Slicer_Loan_Status: #N/A
Name Slicer_Region: #N/A

Sheet Loan_Data
A1: Loan_ID | B1: Customer_Name | C1: Age | D1: Employment_Type | E1: Monthly_Income | F1: Loan_Amount | G1: Loan_Term_Months | H1: Interest_Rate | I1: Loan_Purpose | J1: Credit_Score | K1: Application_Date | L1: Approval_Date | M1: Loan_Status | N1: EMI | O1: Region | P1: Branch | Q1: Repayment_Status | R1: Late_Payments | S1: Outstanding_Balance | T1: Risk Category
A2: LN10854 | B2: Chetna Saxena | C2: 35 | D2: Self-Employed | E2: 15700 | F2: 2000000 | G2: 48 | H2: 21.84 | I2: Vehicle Loan | J2: 450 | K2: 44859 | L2: 2022-10-30 | M2: Approved | N2: 62838.56 | O2: South | P2: Bangalore-Whitefield | Q2: On Track | R2: 1 | S2: 2000000 | T2: Very High Risk | U2: 2. Find and remove the duplicate Loan_ID records. Note how many duplicates you removed. | AM2: 16. Sort the data by Outstanding_Balance from largest to smallest. Which customer has the highest balance? | AV2: Chetna Saxena
A3: LN11033 | B3: Vinod Kaur | C3: 33 | D3: Business Owner | E3: 175715 | F3: 2000000 | G3: 12 | H3: 16.83 | I3: Medical | J3: 879 | K3: 44467 | L3: 2021-10-16 | M3: Approved | N3: 182248.19 | O3: Central | P3: Indore-Main | Q3: Defaulted | R3: 8 | S3: 2000000 | T3: Low Risk | AV3: Vinod Kaur
A4: LN11048 | B4: Vikram Mishra | C4: 40 | D4: Freelancer | E4: 68136 | F4: 2000000 | G4: 60 | H4: 7.85 | I4: Business Expansion | J4: 492 | K4: 44287 | L4: 2021-05-01 | M4: Approved | N4: 40409.37 | O4: South | P4: Hyderabad-Hitech | Q4: Defaulted | R4: 12 | S4: 2000000 | T4: Very High Risk | AV4: Vikram Mishra
A5: LN10668 | B5: Pooja Iyer | C5: 25 | D5: Self-Employed | E5: 98360 | F5: 2000000 | G5: 120 | H5: 10.12 | I5: Debt Consolidation | J5: 788 | K5: 45248 | L5: 2023-12-13 | M5: Pending | N5: 26563.23 | O5: Central | P5: Bhopal-Mp Nagar | Q5: Late | R5: 4 | S5: 1976093.1 | T5: Low Risk | AM5: 17. Filter Repayment_Status to show only Defaulted loans. How many are there? Now add a second filter to show defaults from the North region only.
A6: LN10299 | B6: Vikram Jain | C6: 54 | D6: Salaried | E6: 90978 | F6: 2000000 | G6: 60 | H6: 16.3 | I6: Business Expansion | J6: 748 | K6: 45167 | L6: 2023-09-06 | M6: Approved | N6: 48955.49 | O6: West | P6: Ahmedabad-Cg Road | Q6: On Track | R6: 2 | S6: 1955940.1 | T6: Medium Risk | AN6: Defaulted loans= | AO6: 112
A7: LN11104 | B7: Mohan Malhotra | C7: 58 | D7: Self-Employed | E7: 124468 | F7: 2000000 | G7: 36 | H7: 13.69 | I7: Business Expansion | J7: 515 | K7: 44740 | L7: 2022-07-24 | M7: Approved | N7: 68054.52 | O7: North | P7: Delhi-Connaught | Q7: Closed | R7: 0 | S7: 1877501.9 | T7: Very High Risk | AM7: Loan_ID | AN7: Customer_Name | AO7: Age | AP7: Employment_Type | AQ7: Monthly_Income | AR7: Loan_Amount | AS7: Loan_Term_Months | AT7: Interest_Rate | AU7: Loan_Purpose | AV7: Credit_Score | AW7: Application_Date | AX7: Approval_Date | AY7: Loan_Status | AZ7: EMI | BA7: Region | BB7: Branch | BC7: Repayment_Status | BD7: Late_Payments | BE7: Outstanding_Balance | BG7: Loan_ID | BH7: Customer_Name | BI7: Age | BJ7: Employment_Type | BK7: Monthly_Income | BL7: Loan_Amount | BM7: Loan_Term_Months | BN7: Interest_Rate | BO7: Loan_Purpose | BP7: Credit_Score | BQ7: Application_Date | BR7: Approval_Date | BS7: Loan_Status | BT7: EMI | BU7: Region | BV7: Branch | BW7: Repayment_Status | BX7: Late_Payments | BY7: Outstanding_Balance
A8: LN11156 | B8: Ganesh Mishra | C8: 56 | D8: Self-Employed | E8: 187306 | F8: 2000000 | G8: 12 | H8: 20.93 | I8: Agriculture | J8: 521 | K8: 45228 | L8: 2023-11-19 | M8: Approved | N8: 186160.36 | O8: West | P8: Pune-Shivajinagar | Q8: Closed | R8: 0 | S8: 1832455.7 | T8: Very High Risk | BC8: Defaulted | BU8: North | BW8: Defaulted
A9: LN10511 | B9: Anita Saxena | C9: 65 | D9: Self-Employed | E9: 87806 | F9: 2000000 | G9: 36 | H9: 12.76 | I9: Medical | J9: 615 | K9: 44687 | L9: 2022-05-17 | M9: Approved | N9: 67156.94 | O9: North | P9: Chandigarh-Main | Q9: On Track | R9: 0 | S9: 1818676.3 | T9: High Risk
A10: LN10384 | B10: Mohan Iyer | C10: 30 | D10: Self-Employed | E10: 21867 | F10: 2000000 | G10: 60 | H10: 16.28 | I10: Personal | J10: 537 | K10: 45173 | L10: 2023-09-11 | M10: Rejected | N10: 48934.16 | O10: South | P10: Bangalore-Koramangala | Q10: Closed | R10: 1 | S10: 1779796.3 | T10: Very High Risk | AM10: Loan_ID | AN10: Customer_Name | AO10: Age | AP10: Employment_Type | AQ10: Monthly_Income | AR10: Loan_Amount | AS10: Loan_Term_Months | AT10: Interest_Rate | AU10: Loan_Purpose | AV10: Credit_Score | AW10: Application_Date | AX10: Approval_Date | AY10: Loan_Status | AZ10: EMI | BA10: Region | BB10: Branch | BC10: Repayment_Status | BD10: Late_Payments | BE10: Outstanding_Balance | BG10: Loan_ID | BH10: Customer_Name | BI10: Age | BJ10: Employment_Type | BK10: Monthly_Income | BL10: Loan_Amount | BM10: Loan_Term_Months | BN10: Interest_Rate | BO10: Loan_Purpose | BP10: Credit_Score | BQ10: Application_Date | BR10: Approval_Date | BS10: Loan_Status | BT10: EMI | BU10: Region | BV10: Branch | BW10: Repayment_Status | BX10: Late_Payments | BY10: Outstanding_Balance
A11: LN10696 | B11: Vinod Mishra | C11: 35 | D11: Government Employee | E11: 180098 | F11: 2000000 | G11: 120 | H11: 9.76 | I11: Personal | J11: 744 | K11: 45212 | L11: 2023-10-21 | M11: Approved | N11: 26165.06 | O11: East | P11: Kolkata-Salt Lake | Q11: On Track | R11: 1 | S11: 1740965.9 | T11: Medium Risk | AM11: LN11033 | AN11: Vinod Kaur | AO11: 33 | AP11: Business Owner | AQ11: 175715 | AR11: 2000000 | AS11: 12 | AT11: 16.83 | AU11: Medical | AV11: 879 | AW11: 44467 | AX11: 2021-10-16 | AY11: Approved | AZ11: 182248.19 | BA11: Central | BB11: Indore-Main | BC11: Defaulted | BD11: 8 | BE11: 2000000 | BG11: LN10306 | BH11: Komal Nair | BI11: 39 | BJ11: Self-Employed | BK11: 248648 | BL11: 500000 | BM11: 48 | BN11: 11.32 | BO11: Vehicle Loan | BP11: 377 | BQ11: 45026 | BR11: 2023-05-07 | BS11: Approved | BT11: 13000.6 | BU11: North | BV11: Chandigarh-Main | BW11: Defaulted | BX11: 10 | BY11: 488299.46
A12: LN10446 | B12: Amit Joshi | C12: 28 | D12: Government Employee | E12: 113600 | F12: 2000000 | G12: 36 | H12: 7.73 | I12: Agriculture | J12: 382 | K12: 44778 | L12: 2022-08-21 | M12: Rejected | N12: 62423.92 | O12: North | P12: Delhi-Connaught | Q12: Closed | R12: 0 | S12: 1719092.4 | T12: Very High Risk | AM12: LN11048 | AN12: Vikram Mishra | AO12: 40 | AP12: Freelancer | AQ12: 68136 | AR12: 2000000 | AS12: 60 | AT12: 7.85 | AU12: Business Expansion | AV12: 492 | AW12: 44287 | AX12: 2021-05-01 | AY12: Approved | AZ12: 40409.37 | BA12: South | BB12: Hyderabad-Hitech | BC12: Defaulted | BD12: 12 | BE12: 2000000 | BG12: LN10100 | BH12: Nisha Mishra | BI12: 59 | BJ12: Salaried | BK12: 107259 | BL12: 500000 | BM12: 24 | BN12: 12 | BO12: Agriculture | BP12: 338 | BQ12: 44381 | BR12: 2021-07-26 | BS12: Rejected | BT12: 23536.74 | BU12: North | BV12: Noida-Sector18 | BW12: Defaulted | BX12: 4 | BY12: 457633.87
A13: LN10283 | B13: Manoj Singh | C13: 62 | D13: Government Employee | E13: 47301 | F13: 2000000 | G13: 180 | H13: 14.13 | I13: Education | J13: 810 | K13: 45083 | L13: 2023-07-05 | M13: Approved | N13: 26809.74 | O13: North | P13: Chandigarh-Main | Q13: Late | R13: 11 | S13: 1710454.8 | T13: Low Risk | AM13: LN10380 | AN13: Tarun Chatterjee | AO13: 37 | AP13: Government Employee | AQ13: 87319 | AR13: 2000000 | AS13: 12 | AT13: 16.57 | AU13: Debt Consolidation | AV13: 330 | AW13: 44896 | AX13: 2022-12-16 | AY13: Rejected | AZ13: 182001.62 | BA13: Central | BB13: Nagpur-Dharampeth | BC13: Defaulted | BD13: 3 | BE13: 1672397.1 | BG13: LN10912 | BH13: Sunita Deshpande | BI13: 62 | BJ13: Salaried | BK13: 66491 | BL13: 400000 | BM13: 24 | BN13: 13.91 | BO13: Agriculture | BP13: 502 | BQ13: 45194 | BR13: 2023-10-07 | BS13: Approved | BT13: 19188.15 | BU13: North | BV13: Chandigarh-Main | BW13: Defaulted | BX13: 9 | BY13: 296383.99
A14: LN10239 | B14: Ganesh Chaudhary | C14: 32 | D14: Freelancer | E14: 34322 | F14: 2000000 | G14: 12 | H14: 11.78 | I14: Medical | J14: 567 | K14: 44965 | L14: 2023-02-16 | M14: Approved | N14: 177491.81 | O14: North | P14: Delhi-Connaught | Q14: Late | R14: 5 | S14: 1680514.7 | T14: High Risk | AM14: LN10382 | AN14: Komal Joshi | AO14: 59 | AP14: Government Employee | AQ14: 194319 | AR14: 2000000 | AS14: 48 | AT14: 20.01 | AU14: Business Expansion | AV14: 836 | AW14: 44520 | AX14: 2021-12-03 | AY14: Approved | AZ14: 60871.38 | BA14: South | BB14: Hyderabad-Hitech | BC14: Defaulted | BD14: 12 | BE14: 1506941.8 | BG14: LN10210 | BH14: Vinod Joshi | BI14: 46 | BJ14: Government Employee | BK14: 125326 | BL14: 250000 | BM14: 240 | BN14: 17.4 | BO14: Agriculture | BP14: 374 | BQ14: 44733 | BR14: 2022-06-30 | BS14: Approved | BT14: 3743.24 | BU14: North | BV14: Chandigarh-Main | BW14: Defaulted | BX14: 1 | BY14: 239893.25
A15: LN10392 | B15: Ajay Mehta | C15: 32 | D15: Self-Employed | E15: 61888 | F15: 2000000 | G15: 12 | H15: 13.58 | I15: Business Expansion | J15: 756 | K15: 44612 | L15: 2022-02-23 | M15: Approved | N15: 179179.24 | O15: East | P15: Kolkata-Salt Lake | Q15: On Track | R15: 0 | S15: 1677477.4 | T15: Low Risk | AM15: LN11127 | AN15: Anita Menon | AO15: 32 | AP15: Business Owner | AQ15: 40586 | AR15: 2000000 | AS15: 60 | AT15: 11.99 | AU15: Vehicle Loan | AV15: 378 | AW15: 44332 | AX15: 2021-06-12 | AY15: Approved | AZ15: 44478.79 | BA15: South | BB15: Bangalore-Koramangala | BC15: Defaulted | BD15: 0 | BE15: 1399536.3 | BG15: LN11189 | BH15: Geeta Patel | BI15: 43 | BJ15: Self-Employed | BK15: 144073 | BL15: 300000 | BM15: 120 | BN15: 13.81 | BO15: Home Purchase | BP15: 831 | BQ15: 45070 | BR15: 2023-06-20 | BS15: Approved | BT15: 4623.78 | BU15: North | BV15: Delhi-Connaught | BW15: Defaulted | BX15: 11 | BY15: 233417.57
A16: LN10101 | B16: Naveen Nayak | C16: 51 | D16: Government Employee | E16: 160310 | F16: 2000000 | G16: 12 | H16: 14.02 | I16: Personal | J16: 629 | K16: 44323 | L16: 2021-05-24 | M16: Approved | N16: 179593.06 | O16: Central | P16: Raipur-Main | Q16: On Track | R16: 2 | S16: 1676732.5 | T16: High Risk | AM16: LN10495 | AN16: Amit Shah | AO16: 57 | AP16: Business Owner | AQ16: 246918 | AR16: 1500000 | AS16: 36 | AT16: 14.63 | AU16: Education | AV16: 619 | AW16: 45201 | AX16: 2023-10-26 | AY16: Approved | AZ16: 51726.62 | BA16: West | BB16: Ahmedabad-CG Road | BC16: Defaulted | BD16: 12 | BE16: 1174122.3 | BG16: LN10562 | BH16: Rani Malhotra | BI16: 25 | BJ16: Business Owner | BK16: 248061 | BL16: 200000 | BM16: 48 | BN16: 10.15 | BO16: Agriculture | BP16: 302 | BQ16: 44288 | BR16: 2021-04-18 | BS16: Rejected | BT16: 5086.94 | BU16: North | BV16: Chandigarh-Main | BW16: Defaulted | BX16: 5 | BY16: 181687.02
A17: LN10380 | B17: Tarun Chatterjee | C17: 37 | D17: Government Employee | E17: 87319 | F17: 2000000 | G17: 12 | H17: 16.57 | I17: Debt Consolidation | J17: 330 | K17: 44896 | L17: 2022-12-16 | M17: Rejected | N17: 182001.62 | O17: Central | P17: Nagpur-Dharampeth | Q17: Defaulted | R17: 3 | S17: 1672397.1 | T17: Very High Risk | AM17: LN10026 | AN17: Suresh Jain | AO17: 57 | AP17: Freelancer | AQ17: 177702 | AR17: 1500000 | AS17: 36 | AT17: 20.92 | AU17: Personal | AV17: 466 | AW17: 44877 | AX17: 2022-12-10 | AY17: Pending | AZ17: 56451.01 | BA17: South | BB17: Hyderabad-Hitech | BC17: Defaulted | BD17: 0 | BE17: 941135 | BG17: LN10969 | BH17: Kiran Patel | BI17: 57 | BJ17: Freelancer | BK17: 161537 | BL17: 1000000 | BM17: 12 | BN17: 20.49 | BO17: Agriculture | BP17: 451 | BQ17: 44762 | BR17: 2022-08-10 | BS17: Approved | BT17: 92869.18 | BU17: North | BV17: Noida-Sector18 | BW17: Defaulted | BX17: 1 | BY17: 80595.12
A18: LN10972 | B18: Manoj Gupta | C18: 34 | D18: Self-Employed | F18: 2000000 | G18: 36 | H18: 19.62 | I18: Home Purchase | J18: 806 | K18: 45023 | L18: 2023-04-28 | M18: Rejected | N18: 73940.49 | O18: North | P18: Noida-Sector18 | Q18: Late | R18: 1 | S18: 1600721.4 | T18: Low Risk | AM18: LN10275 | AN18: Bhavna Nayak | AO18: 44 | AP18: Government Employee | AQ18: 22554 | AR18: 1000000 | AS18: 36 | AT18: 14.5 | AU18: Agriculture | AV18: 415 | AW18: 44732 | AX18: 2022-07-13 | AY18: Approved | AZ18: 34420.98 | BA18: West | BB18: Ahmedabad-CG Road | BC18: Defaulted | BD18: 0 | BE18: 876084.47 | BG18: LN10991 | BH18: Harish Mehta | BI18: 40 | BJ18: Government Employee | BK18: 31685 | BL18: 150000 | BM18: 36 | BN18: 16.59 | BO18: Medical | BP18: 749 | BQ18: 45279 | BR18: 2023-12-31 | BS18: Approved | BT18: 5317.35 | BU18: North | BV18: Gurgaon-CyberCity | BW18: Defaulted | BX18: 1 | BY18: 78215.77
A19: LN10700 | B19: Pallavi Nair | C19: 34 | D19: Self-Employed | E19: 140940 | F19: 2000000 | G19: 180 | H19: 19.32 | I19: Business Expansion | J19: 639 | K19: 44744 | L19: 2022-07-25 | M19: Approved | N19: 34125.38 | O19: West | P19: Mumbai-Bandra | Q19: Late | R19: 3 | S19: 1570020.2 | T19: High Risk | U19: 3. The Customer_Name column has extra spaces at the start and end of some names. Use TRIM to fix this, then paste the cleaned values back into the column. | AM19: LN10259 | AN19: Manoj Kaur | AO19: 46 | AP19: Salaried | AQ19: 167836 | AR19: 1500000 | AS19: 48 | AT19: 12.48 | AU19: Personal | AV19: 847 | AW19: 44545 | AX19: 2022-01-13 | AY19: Approved | AZ19: 39855.19 | BA19: West | BB19: Pune-Shivajinagar | BC19: Defaulted | BD19: 8 | BE19: 818476.25 | BG19: LN10369 | BH19: Lakshmi Jain | BI19: 49 | BJ19: Freelancer | BK19: 242496 | BL19: 75000 | BM19: 48 | BN19: 18.34 | BO19: Home Purchase | BP19: 691 | BQ19: 44850 | BR19: 2022-11-05 | BS19: Approved | BT19: 2216.47 | BU19: North | BV19: Noida-Sector18 | BW19: Defaulted | BX19: 8 | BY19: 71010.35
A20: LN10720 | B20: Tarun Kapoor | C20: 28 | D20: Salaried | E20: 52387 | F20: 2000000 | G20: 60 | H20: 15.43 | I20: Vehicle Loan | J20: 810 | K20: 44802 | L20: 2022-09-06 | M20: Approved | N20: 48032.48 | O20: North | P20: Gurgaon-Cybercity | Q20: Late | R20: 5 | S20: 1567707.7 | T20: Low Risk | AM20: LN10515 | AN20: Komal Shah | AO20: 62 | AP20: Freelancer | AQ20: 222360 | AR20: 1000000 | AS20: 36 | AT20: 7.54 | AU20: Personal | AV20: 612 | AW20: 44520 | AX20: 2021-11-30 | AY20: Approved | AZ20: 31124.59 | BA20: East | BB20: Guwahati-Main | BC20: Defaulted | BD20: 1 | BE20: 803915.08 | BG20: LN11106 | BH20: Siddharth Deshpande | BI20: 55 | BJ20: Self-Employed | BK20: 190047 | BL20: 1000000 | BM20: 240 | BN20: 17.4 | BO20: Personal | BP20: 531 | BQ20: 44869 | BR20: 2022-11-23 | BS20: Rejected | BT20: 14972.95 | BU20: North | BV20: Gurgaon-CyberCity | BW20: Defaulted | BX20: 7 | BY20: 70179.8
A21: LN11187 | B21: Ganesh Kulkarni | C21: 23 | D21: Government Employee | E21: 51514 | F21: 2000000 | G21: 120 | H21: 10.32 | I21: Education | J21: 520 | K21: 44347 | L21: 2021-06-10 | M21: Approved | N21: 26785.82 | O21: Central | P21: Lucknow-Hazratganj | Q21: On Track | R21: 2 | S21: 1566069.7 | T21: Very High Risk | AM21: LN10845 | AN21: Meena Kaur | AO21: 61 | AP21: Freelancer | AQ21: 152207 | AR21: 1500000 | AS21: 48 | AT21: 8.35 | AU21: Agriculture | AV21: 558 | AW21: 44505 | AX21: 2021-11-09 | AY21: Approved | AZ21: 36866.32 | BA21: West | BB21: Pune-Shivajinagar | BC21: Defaulted | BD21: 11 | BE21: 803226.55 | BG21: LN10314 | BH21: Tarun Singh | BI21: 58 | BJ21: Self-Employed | BK21: 29656 | BL21: 100000 | BM21: 60 | BN21: 20.88 | BO21: Debt Consolidation | BP21: 877 | BQ21: 45116 | BR21: 2023-07-31 | BS21: Approved | BT21: 2698.59 | BU21: North | BV21: Noida-Sector18 | BW21: Defaulted | BX21: 1 | BY21: 68426.5
A22: LN11167 | B22: Rajesh Patel | C22: 64 | D22: Salaried | E22: 241200 | F22: 2000000 | G22: 12 | H22: 8.71 | I22: Education | J22: 899 | K22: 45181 | L22: 2023-10-10 | M22: Approved | N22: 174634.11 | O22: North | P22: Delhi-Connaught | Q22: Late | R22: 11 | S22: 1528487.9 | T22: Low Risk | AM22: LN11080 | AN22: Suresh Tiwari | AO22: 35 | AP22: Salaried | AQ22: 248651 | AR22: 1000000 | AS22: 12 | AT22: 7.64 | AU22: Medical | AV22: 583 | AW22: 44648 | AX22: 2022-04-19 | AY22: Approved | AZ22: 86822.07 | BA22: East | BB22: Patna-Boring Road | BC22: Defaulted | BD22: 3 | BE22: 765580.41 | BG22: LN10583 | BH22: Deepa Patel | BI22: 36 | BJ22: Freelancer | BK22: 34514 | BL22: 150000 | BM22: 48 | BN22: 9.88 | BO22: Business Expansion | BP22: 364 | BQ22: 44246 | BR22: 2021-03-12 | BS22: Approved | BT22: 3795.75 | BU22: North | BV22: Delhi-Connaught | BW22: Defaulted | BX22: 7 | BY22: 57763.27
A23: LN10006 | B23: Tarun Chaudhary | C23: 65 | D23: Business Owner | E23: 235948 | F23: 2000000 | G23: 12 | H23: 10.82 | I23: Home Purchase | J23: 623 | K23: 44841 | L23: 2022-10-16 | M23: Approved | N23: 176595.44 | O23: West | P23: Pune-Shivajinagar | Q23: Grace Period | R23: 0 | S23: 1523192.3 | T23: High Risk | AM23: LN10252 | AN23: Nisha Kaur | AO23: 30 | AP23: Government Employee | AQ23: 245511 | AR23: 750000 | AS23: 12 | AT23: 10.02 | AU23: Personal | AV23: 359 | AW23: 44935 | AX23: 2023-02-03 | AY23: Approved | AZ23: 65943.89 | BA23: South | BB23: Bangalore-Koramangala | BC23: Defaulted | BD23: 7 | BE23: 750000 | BG23: LN10200 | BH23: Pallavi Deshpande | BI23: 37 | BJ23: Freelancer | BK23: 143308 | BL23: 100000 | BM23: 60 | BN23: 16.6 | BO23: Debt Consolidation | BP23: 762 | BQ23: 44766 | BR23: 2022-08-18 | BS23: Rejected | BT23: 2463.8 | BU23: North | BV23: Delhi-Connaught | BW23: Defaulted | BX23: 6 | BY23: 29042.56
A24: LN10382 | B24: Komal Joshi | C24: 59 | D24: Government Employee | E24: 194319 | F24: 2000000 | G24: 48 | H24: 20.01 | I24: Business Expansion | J24: 836 | K24: 44520 | L24: 2021-12-03 | M24: Approved | N24: 60871.38 | O24: South | P24: Hyderabad-Hitech | Q24: Defaulted | R24: 12 | S24: 1506941.8 | T24: Low Risk | AM24: LN10704 | AN24: Suresh Mishra | AO24: 53 | AP24: Business Owner | AQ24: 84573 | AR24: 2000000 | AS24: 24 | AT24: 18.94 | AU24: Education | AV24: 450 | AW24: 45176 | AX24: 2023-10-06 | AY24: Rejected | AZ24: 100758.94 | BA24: East | BB24: Kolkata-Salt Lake | BC24: Defaulted | BD24: 6 | BE24: 730437.36 | BG24: LN10195 | BH24: Jyoti Malhotra | BI24: 50 | BJ24: Freelancer | BK24: 58844 | BL24: 75000 | BM24: 12 | BN24: 19.04 | BO24: Personal | BP24: 599 | BQ24: 44788 | BR24: 2022-08-23 | BS24: Rejected | BT24: 6913.18 | BU24: North | BV24: Noida-Sector18 | BW24: Defaulted | BX24: 3 | BY24: 25225.1
A25: LN10469 | B25: Sanjay Mehta | C25: 58 | D25: Freelancer | E25: 103784 | F25: 1500000 | G25: 24 | H25: 18.11 | I25: Home Purchase | J25: 442 | K25: 45019 | L25: 2023-04-25 | M25: Approved | N25: 74965.9 | O25: Central | P25: Indore-Main | Q25: Closed | R25: 1 | S25: 1500000 | T25: Very High Risk | AM25: LN10917 | AN25: Suresh Chatterjee | AO25: 61 | AP25: Self-Employed | AQ25: 164686 | AR25: 1000000 | AS25: 36 | AT25: 12.19 | AU25: Personal | AV25: 705 | AW25: 44863 | AX25: 2022-11-17 | AY25: Approved | AZ25: 33305.13 | BA25: South | BB25: Bangalore-Whitefield | BC25: Defaulted | BD25: 9 | BE25: 700253.83 | BG25: LN10018 | BH25: Smita Banerjee | BI25: 49 | BJ25: Government Employee | BK25: 188505 | BL25: 1500000 | BM25: 180 | BN25: 9.74 | BO25: Business Expansion | BP25: 522 | BQ25: 44321 | BR25: 2021-05-31 | BS25: Pending | BT25: 15881.33 | BU25: North | BV25: Chandigarh-Main | BW25: Defaulted | BX25: 11 | BY25: 0
A26: LN10580 | B26: Chetna Shah | C26: 26 | D26: Government Employee | E26: 48619 | F26: 1500000 | G26: 24 | H26: 9.35 | I26: Personal | J26: 835 | K26: 45288 | L26: 2024-01-19 | M26: Rejected | N26: 68768.24 | O26: East | P26: Kolkata-Salt Lake | Q26: On Track | R26: 2 | S26: 1500000 | T26: Low Risk | AM26: LN10582 | AN26: Jyoti Shetty | AO26: 55 | AP26: Salaried | AQ26: 246683 | AR26: 1500000 | AS26: 48 | AT26: 8.18 | AU26: Debt Consolidation | AV26: 845 | AW26: 44595 | AX26: 2022-02-16 | AY26: Approved | AZ26: 36746.25 | BA26: West | BB26: Pune-Shivajinagar | BC26: Defaulted | BD26: 0 | BE26: 673209.38 | BG26: LN10197 | BH26: Chetna Verma | BI26: 41 | BJ26: Salaried | BK26: 132894 | BL26: 200000 | BM26: 84 | BN26: 20 | BO26: Vehicle Loan | BP26: 749 | BQ26: 44915 | BR26: 2023-01-19 | BS26: Approved | BT26: 4441.24 | BU26: North | BV26: Delhi-Dwarka | BW26: Defaulted | BX26: 3 | BY26: 0
A27: LN11020 | B27: Smita Dubey | C27: 31 | D27: Self-Employed | E27: 208425 | F27: 2000000 | G27: 120 | H27: 13.58 | I27: Home Purchase | J27: 442 | K27: 45015 | L27: 2023-04-13 | M27: Approved | N27: 30550.22 | O27: East | P27: Patna-Boring Road | Q27: On Track | R27: 2 | S27: 1477591.2 | T27: Very High Risk | AM27: LN10739 | AN27: Pallavi Joshi | AO27: 54 | AP27: Salaried | AQ27: 180528 | AR27: 750000 | AS27: 120 | AT27: 19.72 | AU27: Business Expansion | AV27: 866 | AW27: 44388 | AX27: 2021-07-14 | AY27: Rejected | AZ27: 14355.21 | BA27: South | BB27: Chennai-Adyar | BC27: Defaulted | BD27: 3 | BE27: 607883.42 | BG27: LN10211 | BH27: Amit Reddy | BI27: 47 | BJ27: Government Employee | BK27: 90101 | BL27: 1000000 | BM27: 240 | BN27: 18.62 | BO27: Debt Consolidation | BP27: 711 | BQ27: 44509 | BR27: 2021-11-20 | BS27: Rejected | BT27: 15911.88 | BU27: North | BV27: Chandigarh-Main | BW27: Defaulted | BX27: 8 | BY27: 0
A28: LN10930 | B28: Smita Pillai | C28: 58 | D28: Business Owner | E28: 249158 | F28: 1500000 | G28: 36 | H28: 10.24 | I28: Education | J28: 511 | K28: 45289 | L28: 2024-01-20 | M28: Rejected | N28: 48569.97 | O28: East | P28: Kolkata-Salt Lake | Q28: Late | R28: 1 | S28: 1456287 | T28: Very High Risk | AM28: LN10306 | AN28: Komal Nair | AO28: 39 | AP28: Self-Employed | AQ28: 248648 | AR28: 500000 | AS28: 48 | AT28: 11.32 | AU28: Vehicle Loan | AV28: 377 | AW28: 45026 | AX28: 2023-05-07 | AY28: Approved | AZ28: 13000.6 | BA28: North | BB28: Chandigarh-Main | BC28: Defaulted | BD28: 10 | BE28: 488299.46 | BG28: LN10216 | BH28: Chetna Sharma | BI28: 24 | BJ28: Salaried | BK28: 79107 | BL28: 50000 | BM28: 180 | BN28: 12.78 | BO28: Education | BP28: 483 | BQ28: 45055 | BR28: 2023-05-19 | BS28: Approved | BT28: 625.4 | BU28: North | BV28: Chandigarh-Main | BW28: Defaulted | BX28: 12 | BY28: 0
A29: LN10342 | B29: Sarala Reddy | C29: 23 | D29: Freelancer | E29: 152358 | F29: 2000000 | G29: 24 | H29: 9.01 | I29: Education | J29: 386 | K29: 44778 | L29: 2022-08-22 | M29: Approved | N29: 91378.66 | O29: West | P29: Pune-Shivajinagar | Q29: Late | R29: 3 | S29: 1424314.4 | T29: Very High Risk | AM29: LN10100 | AN29: Nisha Mishra | AO29: 59 | AP29: Salaried | AQ29: 107259 | AR29: 500000 | AS29: 24 | AT29: 12 | AU29: Agriculture | AV29: 338 | AW29: 44381 | AX29: 2021-07-26 | AY29: Rejected | AZ29: 23536.74 | BA29: North | BB29: Noida-Sector18 | BC29: Defaulted | BD29: 4 | BE29: 457633.87 | BG29: LN10406 | BH29: Madhuri Chatterjee | BI29: 42 | BJ29: Self-Employed | BK29: 216714 | BL29: 75000 | BM29: 240 | BN29: 17.31 | BO29: Education | BP29: 510 | BQ29: 45266 | BR29: 2023-12-12 | BS29: Pending | BT29: 1117.82 | BU29: North | BV29: Gurgaon-CyberCity | BW29: Defaulted | BX29: 6 | BY29: 0
A30: LN11011 | B30: Sunil Rao | C30: 23 | D30: Self-Employed | E30: 226347 | F30: 2000000 | G30: 24 | H30: 11.02 | I30: Education | J30: 682 | K30: 44375 | L30: 2021-07-28 | M30: Pending | N30: 93234.25 | O30: North | P30: Delhi-Dwarka | Q30: Late | R30: 9 | S30: 1412624.2 | T30: Medium Risk | U30: 4. Employment_Type has inconsistent casing — some entries are in all caps, others are all lowercase. Use PROPER to standardise them, then paste the values back. | AM30: LN10578 | AN30: Pooja Jain | AO30: 34 | AP30: Salaried | AQ30: 228983 | AR30: 750000 | AS30: 60 | AT30: 19.22 | AU30: Personal | AV30: 539 | AW30: 45206 | AX30: 2023-11-01 | AY30: Approved | AZ30: 19546.32 | BA30: West | BB30: Pune-Shivajinagar | BC30: Defaulted | BD30: 0 | BE30: 450941.3 | BG30: LN10527 | BH30: Ashok Nair | BI30: 35 | BJ30: Business Owner | BK30: 62357 | BL30: 100000 | BM30: 240 | BN30: 19.43 | BO30: Personal | BP30: 897 | BQ30: 44566 | BR30: 2022-01-21 | BS30: Pending | BT30: 1654.2 | BU30: North | BV30: Chandigarh-Main | BW30: Defaulted | BX30: 12 | BY30: 0
A31: LN10772 | B31: Lakshmi Rao | C31: 49 | D31: Freelancer | E31: 163547 | F31: 2000000 | G31: 84 | H31: 11.68 | I31: Home Purchase | J31: 810 | K31: 45268 | L31: 2023-12-20 | M31: Approved | N31: 34964.12 | O31: South | P31: Hyderabad-Hitech | Q31: On Track | R31: 2 | S31: 1402113.6 | T31: Low Risk | AM31: LN10462 | AN31: Madhuri Rao | AO31: 52 | AP31: Government Employee | AQ31: 192814 | AR31: 500000 | AS31: 60 | AT31: 14.05 | AU31: Medical | AV31: 367 | AW31: 44997 | AX31: 2023-03-20 | AY31: Rejected | AZ31: 11647.09 | BA31: South | BB31: Hyderabad-Hitech | BC31: Defaulted | BD31: 1 | BE31: 447588.09 | BG31: LN10607 | BH31: Rekha Kaur | BI31: 26 | BJ31: Government Employee | BK31: 116301 | BL31: 150000 | BM31: 180 | BN31: 9.08 | BO31: Agriculture | BP31: 611 | BQ31: 44560 | BR31: 2022-01-03 | BS31: Approved | BT31: 1528.55 | BU31: North | BV31: Delhi-Dwarka | BW31: Defaulted | BX31: 1 | BY31: 0
A32: LN11127 | B32: Anita Menon | C32: 32 | D32: Business Owner | E32: 40586 | F32: 2000000 | G32: 60 | H32: 11.99 | I32: Vehicle Loan | J32: 378 | K32: 44332 | L32: 2021-06-12 | M32: Approved | N32: 44478.79 | O32: South | P32: Bangalore-Koramangala | Q32: Defaulted | R32: 0 | S32: 1399536.3 | T32: Very High Risk | AM32: LN10491 | AN32: Anil Tiwari | AO32: 53 | AP32: Business Owner | AQ32: 215492 | AR32: 1500000 | AS32: 60 | AT32: 18.47 | AU32: Debt Consolidation | AV32: 664 | AW32: 45244 | AX32: 2023-11-25 | AY32: Approved | AZ32: 38474.7 | BA32: West | BB32: Surat-Ring Road | BC32: Defaulted | BD32: 6 | BE32: 426555.87 | BG32: LN10657 | BH32: Abhishek Nair | BI32: 51 | BJ32: Freelancer | BK32: 87146 | BL32: 1000000 | BM32: 180 | BN32: 12.83 | BO32: Vehicle Loan | BP32: 419 | BQ32: 45240 | BR32: 2023-11-20 | BS32: Approved | BT32: 12540.77 | BU32: North | BV32: Delhi-Connaught | BW32: Defaulted | BX32: 7 | BY32: 0
A33: LN10633 | B33: Rohit Jain | C33: 54 | D33: Freelancer | E33: 181456 | F33: 1500000 | G33: 84 | H33: 17.6 | I33: Debt Consolidation | J33: 734 | K33: 44937 | L33: 2023-02-03 | M33: Approved | N33: 31176.06 | O33: South | P33: Bangalore-Whitefield | Q33: On Track | R33: 1 | S33: 1387766.2 | T33: Medium Risk | AM33: LN10835 | AN33: Pooja Menon | AO33: 48 | AP33: Salaried | AQ33: 162392 | AR33: 2000000 | AS33: 84 | AT33: 11.29 | AU33: Medical | AV33: 721 | AW33: 44730 | AX33: 2022-06-22 | AY33: Approved | AZ33: 34550.59 | BA33: West | BB33: Ahmedabad-CG Road | BC33: Defaulted | BD33: 6 | BE33: 414127.92 | BG33: LN10804 | BH33: Deepa Menon | BI33: 30 | BJ33: Government Employee | BK33: 75433 | BL33: 200000 | BM33: 240 | BN33: 10.56 | BO33: Medical | BP33: 445 | BQ33: 45126 | BR33: 2023-07-25 | BS33: Approved | BT33: 2004.83 | BU33: North | BV33: Delhi-Dwarka | BW33: Defaulted | BX33: 11 | BY33: 0
A34: LN10279 | B34: Jyoti Dubey | C34: 42 | D34: Salaried | E34: 145383 | F34: 1500000 | G34: 12 | H34: 8.99 | I34: Debt Consolidation | J34: 336 | K34: 44820 | L34: 2022-10-05 | M34: Approved | N34: 131170.26 | O34: Central | P34: Lucknow-Hazratganj | Q34: On Track | R34: 0 | S34: 1381946.8 | T34: Very High Risk | AM34: LN10942 | AN34: Pallavi Yadav | AO34: 64 | AP34: Government Employee | AQ34: 151293 | AR34: 500000 | AS34: 60 | AT34: 18.52 | AU34: Education | AV34: 635 | AW34: 44267 | AX34: 2021-04-07 | AY34: Approved | AZ34: 12838.58 | BA34: West | BB34: Pune-Shivajinagar | BC34: Defaulted | BD34: 10 | BE34: 396007.5 | BG34: LN10986 | BH34: Rajesh Malhotra | BI34: 48 | BJ34: Freelancer | BK34: 87898 | BL34: 150000 | BM34: 180 | BN34: 11.17 | BO34: Home Purchase | BP34: 704 | BQ34: 44653 | BR34: 2022-04-07 | BS34: Approved | BT34: 1720.94 | BU34: North | BV34: Gurgaon-CyberCity | BW34: Defaulted | BX34: 2 | BY34: 0
A35: LN11079 | B35: Kavitha Joshi | C35: 33 | D35: Salaried | E35: 109721 | F35: 2000000 | G35: 12 | H35: 8.1 | I35: Vehicle Loan | J35: 584 | K35: 44457 | L35: 2021-10-16 | M35: Approved | N35: 174069.34 | O35: North | P35: Chandigarh-Main | Q35: On Track | R35: 2 | S35: 1373350.4 | T35: High Risk | AM35: LN10817 | AN35: Ramesh Deshpande | AO35: 39 | AP35: Business Owner | AQ35: 234154 | AR35: 750000 | AS35: 60 | AT35: 20.71 | AU35: Medical | AV35: 548 | AW35: 44433 | AX35: 2021-09-19 | AY35: Approved | AZ35: 20167.86 | BA35: East | BB35: Kolkata-Salt Lake | BC35: Defaulted | BD35: 7 | BE35: 386978.52
A36: LN11135 | B36: Madhuri Shetty | C36: 26 | D36: Freelancer | E36: 95841 | F36: 1500000 | G36: 60 | H36: 13.4 | I36: Home Purchase | J36: 591 | K36: 44478 | L36: 2021-10-28 | M36: Approved | N36: 34437.54 | O36: East | P36: Kolkata-Salt Lake | Q36: On Track | R36: 2 | S36: 1345031.1 | T36: High Risk | AM36: LN10603 | AN36: Pallavi Joshi | AO36: 56 | AP36: Business Owner | AQ36: 17237 | AR36: 2000000 | AS36: 60 | AT36: 11.59 | AU36: Medical | AV36: 713 | AW36: 44221 | AX36: 2021-02-12 | AZ36: 44075.63 | BA36: West | BB36: Surat-Ring Road | BC36: Defaulted | BD36: 12 | BE36: 373609.25
A37: LN10637 | B37: Kiran Kapoor | C37: 22 | D37: Business Owner | E37: 33308 | F37: 2000000 | G37: 120 | H37: 15.11 | I37: Business Expansion | J37: 741 | K37: 44472 | L37: 2021-10-12 | M37: Rejected | N37: 32401.85 | O37: South | P37: Bangalore-Whitefield | Q37: On Track | R37: 1 | S37: 1329281.7 | T37: Medium Risk | AM37: LN11124 | AN37: Usha Sharma | AO37: 49 | AP37: Salaried | AQ37: 34950 | AR37: 2000000 | AS37: 60 | AT37: 15.26 | AU37: Debt Consolidation | AV37: 316 | AW37: 44301 | AX37: 2021-05-03 | AY37: Approved | AZ37: 47853.25 | BA37: Central | BB37: Nagpur-Dharampeth | BC37: Defaulted | BD37: 12 | BE37: 363418.85
A38: LN11055 | B38: Rajesh Iyer | C38: 53 | D38: Self-Employed | E38: 33928 | F38: 1500000 | G38: 60 | H38: 11.01 | I38: Debt Consolidation | J38: 610 | K38: 44588 | L38: 2022-01-30 | M38: Approved | N38: 32621.12 | O38: South | P38: Kochi-Mg Road | Q38: Grace Period | R38: 2 | S38: 1323845.9 | T38: High Risk | AM38: LN10034 | AN38: Mohan Mehta | AO38: 23 | AP38: Salaried | AQ38: 79184 | AR38: 400000 | AS38: 24 | AT38: 14.1 | AU38: Personal | AV38: 693 | AW38: 44208 | AX38: 2021-02-08 | AY38: Approved | AZ38: 19224.06 | BA38: West | BB38: Ahmedabad-CG Road | BC38: Defaulted | BD38: 3 | BE38: 330793.38
A39: LN10712 | B39: Usha Tiwari | C39: 65 | D39: Freelancer | E39: 160268 | F39: 1500000 | G39: 60 | H39: 20.83 | I39: Business Expansion | J39: 532 | K39: 45265 | L39: 2023-12-20 | M39: Approved | N39: 40436.73 | O39: West | P39: Mumbai-Bandra | Q39: On Track | R39: 1 | S39: 1318034.7 | T39: Very High Risk | AM39: LN10354 | AN39: Amit Saxena | AO39: 60 | AP39: Self-Employed | AQ39: 112359 | AR39: 2000000 | AS39: 24 | AT39: 11.11 | AU39: Agriculture | AV39: 393 | AW39: 44319 | AX39: 2021-05-07 | AY39: Approved | AZ39: 93317.85 | BA39: Central | BB39: Nagpur-Dharampeth | BC39: Defaulted | BD39: 12 | BE39: 320278.7
A40: LN10324 | B40: Mohan Singh | C40: 60 | D40: Government Employee | E40: 150217 | F40: 1500000 | G40: 48 | H40: 16.42 | I40: Home Purchase | J40: 668 | K40: 44762 | L40: 2022-08-16 | M40: Approved | N40: 42833.77 | O40: South | P40: Bangalore-Koramangala | Q40: Late | R40: 2 | S40: 1307248 | T40: Medium Risk | AM40: LN10724 | AN40: Kiran Kaur | AO40: 26 | AP40: Self-Employed | AQ40: 116770 | AR40: 400000 | AS40: 24 | AT40: 12.56 | AU40: Agriculture | AV40: 847 | AW40: 44418 | AX40: 2021-08-25 | AY40: Approved | AZ40: 18934.17 | BA40: West | BB40: Mumbai-Andheri | BC40: Defaulted | BD40: 1 | BE40: 314796.23
A41: LN10956 | B41: Rani Tiwari | C41: 64 | D41: Business Owner | E41: 42253 | F41: 2000000 | G41: 180 | H41: 15.63 | I41: Debt Consolidation | J41: 831 | K41: 44398 | L41: 2021-08-11 | M41: Approved | N41: 28859.72 | O41: West | P41: Mumbai-Andheri | Q41: Closed | R41: 2 | S41: 1298708.8 | T41: Low Risk | AM41: LN10912 | AN41: Sunita Deshpande | AO41: 62 | AP41: Salaried | AQ41: 66491 | AR41: 400000 | AS41: 24 | AT41: 13.91 | AU41: Agriculture | AV41: 502 | AW41: 45194 | AX41: 2023-10-07 | AY41: Approved | AZ41: 19188.15 | BA41: North | BB41: Chandigarh-Main | BC41: Defaulted | BD41: 9 | BE41: 296383.99
A42: LN10225 | B42: Divya Patel | C42: 47 | D42: Freelancer | E42: 160739 | F42: 1500000 | G42: 240 | H42: 11.12 | I42: Agriculture | J42: 404 | K42: 44652 | L42: 2022-04-08 | M42: Approved | N42: 15605.51 | O42: South | P42: Bangalore-Koramangala | Q42: On Track | R42: 0 | S42: 1289325.6 | T42: Very High Risk | AM42: LN10385 | AN42: Sunil Saxena | AO42: 63 | AP42: Business Owner | AQ42: 63228 | AR42: 300000 | AS42: 180 | AT42: 14.37 | AU42: Education | AV42: 497 | AW42: 44749 | AX42: 2022-07-23 | AY42: Approved | AZ42: 4070.07 | BA42: South | BB42: Bangalore-Koramangala | BC42: Defaulted | BD42: 6 | BE42: 289010.81
A43: LN10341 | B43: Manoj Gupta | C43: 33 | D43: Salaried | E43: 47778 | F43: 1500000 | G43: 48 | H43: 17.1 | I43: Vehicle Loan | J43: 515 | K43: 44327 | L43: 2021-05-29 | M43: Rejected | N43: 43360.21 | O43: South | P43: Hyderabad-Hitech | Q43: On Track | R43: 0 | S43: 1265854.9 | T43: Very High Risk | AM43: LN10824 | AN43: Rohit Mishra | AO43: 28 | AP43: Self-Employed | AQ43: 92948 | AR43: 400000 | AS43: 84 | AT43: 8.2 | AU43: Debt Consolidation | AV43: 592 | AW43: 44490 | AX43: 2021-10-25 | AY43: Approved | AZ43: 6274.42 | BA43: East | BB43: Patna-Boring Road | BC43: Defaulted | BD43: 5 | BE43: 275766.48
A44: LN10248 | B44: Meena Mehta | C44: 58 | D44: Government Employee | E44: 167745 | F44: 2000000 | G44: 24 | H44: 20.91 | I44: Vehicle Loan | J44: 592 | K44: 44981 | L44: 2023-03-19 | M44: Approved | N44: 102682.91 | O44: Central | P44: Nagpur-Dharampeth | Q44: On Track | R44: 1 | S44: 1260683.1 | T44: High Risk | AM44: LN10621 | AN44: Rajesh Kaur | AO44: 63 | AP44: Business Owner | AQ44: 18140 | AR44: 300000 | AS44: 48 | AT44: 14.15 | AU44: Vehicle Loan | AV44: 585 | AW44: 44644 | AX44: 2022-04-09 | AY44: Rejected | AZ44: 8220.53 | BA44: Central | BB44: Nagpur-Dharampeth | BC44: Defaulted | BD44: 0 | BE44: 270406.09
A45: LN11147 | B45: Divya Tiwari | C45: 22 | D45: Freelancer | E45: 220965 | F45: 2000000 | G45: 240 | H45: 8.45 | I45: Agriculture | J45: 656 | K45: 44761 | L45: 2022-08-17 | M45: Approved | N45: 17293.23 | O45: East | P45: Kolkata-Salt Lake | Q45: On Track | R45: 1 | S45: 1206240.7 | T45: Medium Risk | U45: 5. Loan_Purpose has hidden non-breaking space characters in some rows. Use a combination of TRIM, CLEAN, and SUBSTITUTE with CHAR(160) to remove them. | AM45: LN10426 | AN45: Sunita Banerjee | AO45: 61 | AP45: Salaried | AQ45: 90187 | AR45: 400000 | AS45: 24 | AT45: 9.34 | AU45: Vehicle Loan | AV45: 584 | AW45: 44760 | AX45: 2022-08-17 | AY45: Approved | AZ45: 18336.36 | BA45: East | BB45: Kolkata-Salt Lake | BC45: Defaulted | BD45: 9 | BE45: 267978.21
A46: LN10234 | B46: Vinod Reddy | C46: 23 | D46: Self-Employed | E46: 168776 | F46: 1500000 | G46: 36 | H46: 18.73 | I46: Medical | J46: 374 | K46: 44886 | L46: 2022-12-03 | M46: Approved | N46: 54779.48 | O46: East | P46: Patna-Boring Road | Q46: Closed | R46: 2 | S46: 1204190.8 | T46: Very High Risk | AM46: LN10210 | AN46: Vinod Joshi | AO46: 46 | AP46: Government Employee | AQ46: 125326 | AR46: 250000 | AS46: 240 | AT46: 17.4 | AU46: Agriculture | AV46: 374 | AW46: 44733 | AX46: 2022-06-30 | AY46: Approved | AZ46: 3743.24 | BA46: North | BB46: Chandigarh-Main | BC46: Defaulted | BD46: 1 | BE46: 239893.25
A47: LN10098 | B47: Tarun Rao | C47: 55 | D47: Government Employee | F47: 2000000 | G47: 84 | H47: 12.59 | I47: Education | J47: 541 | K47: 44552 | L47: 2022-01-13 | M47: Approved | N47: 35939.61 | O47: North | P47: Delhi-Dwarka | Q47: On Track | R47: 1 | S47: 1191358.8 | T47: Very High Risk | AM47: LN11189 | AN47: Geeta Patel | AO47: 43 | AP47: Self-Employed | AQ47: 144073 | AR47: 300000 | AS47: 120 | AT47: 13.81 | AU47: Home Purchase | AV47: 831 | AW47: 45070 | AX47: 2023-06-20 | AY47: Approved | AZ47: 4623.78 | BA47: North | BB47: Delhi-Connaught | BC47: Defaulted | BD47: 11 | BE47: 233417.57
A48: LN10662 | B48: Sanjay Dubey | C48: 30 | D48: Government Employee | E48: 143566 | F48: 1500000 | G48: 84 | H48: 15.08 | I48: Medical | J48: 851 | K48: 44288 | L48: 2021-04-12 | N48: 29012.5 | O48: Central | P48: Bhopal-Mp Nagar | Q48: On Track | R48: 2 | S48: 1186665 | T48: Low Risk | AM48: LN10655 | AN48: Rohit Iyer | AO48: 65 | AP48: Self-Employed | AQ48: 113711 | AR48: 300000 | AS48: 36 | AT48: 20.93 | AU48: Vehicle Loan | AV48: 664 | AW48: 45252 | AX48: 2023-12-15 | AY48: Approved | AZ48: 11291.74 | BA48: West | BB48: Mumbai-Bandra | BC48: Defaulted | BD48: 0 | BE48: 228862.04
A49: LN10454 | B49: Lakshmi Chaudhary | C49: 40 | D49: Government Employee | E49: 56101 | F49: 2000000 | G49: 36 | H49: 15.88 | I49: Personal | J49: 388 | K49: 45166 | L49: 2023-09-26 | M49: Rejected | N49: 70195.64 | O49: West | P49: Surat-Ring Road | Q49: On Track | R49: 1 | S49: 1178711 | T49: Very High Risk | AM49: LN10909 | AN49: Chetna Pillai | AO49: 45 | AP49: Salaried | AQ49: 119462 | AR49: 1000000 | AS49: 24 | AT49: 21.3 | AU49: Vehicle Loan | AV49: 577 | AW49: 44359 | AX49: 2021-07-10 | AY49: Approved | AZ49: 51533.12 | BA49: Central | BB49: Lucknow-Hazratganj | BC49: Defaulted | BD49: 11 | BE49: 211543.26
A50: LN10495 | B50: Amit Shah | C50: 57 | D50: Business Owner | E50: 246918 | F50: 1500000 | G50: 36 | H50: 14.63 | I50: Education | J50: 619 | K50: 45201 | L50: 2023-10-26 | M50: Approved | N50: 51726.62 | O50: West | P50: Ahmedabad-Cg Road | Q50: Defaulted | R50: 12 | S50: 1174122.3 | T50: High Risk | AM50: LN10054 | AN50: Meena Chatterjee | AO50: 27 | AP50: Self-Employed | AQ50: 46051 | AR50: 500000 | AS50: 120 | AT50: 16.29 | AU50: Personal | AV50: 835 | AW50: 45075 | AX50: 2023-06-10 | AY50: Approved | AZ50: 8466.24 | BA50: West | BB50: Ahmedabad-CG Road | BC50: Defaulted | BD50: 7 | BE50: 210454.59
A51: LN10708 | B51: Kavitha Reddy | C51: 44 | D51: Business Owner | E51: 237495 | F51: 2000000 | G51: 36 | H51: 11.77 | I51: Education | J51: 864 | K51: 44311 | L51: 2021-05-21 | M51: Approved | N51: 66209.13 | O51: West | P51: Mumbai-Bandra | Q51: Closed | R51: 0 | S51: 1165765 | T51: Low Risk | AM51: LN10378 | AN51: Suresh Patel | AO51: 40 | AP51: Freelancer | AQ51: 75599 | AR51: 300000 | AS51: 240 | AT51: 21.66 | AU51: Vehicle Loan | AV51: 623 | AW51: 44578 | AX51: 2022-01-26 | AY51: Approved | AZ51: 5489.99 | BA51: West | BB51: Surat-Ring Road | BC51: Defaulted | BD51: 8 | BE51: 191298.2
A52: LN10595 | B52: Rekha Chatterjee | C52: 51 | D52: Self-Employed | E52: 111899 | F52: 2000000 | G52: 84 | H52: 17.08 | I52: Debt Consolidation | J52: 366 | K52: 44589 | L52: 2022-02-17 | M52: Approved | N52: 40964.13 | O52: North | P52: Delhi-Dwarka | Q52: Late | R52: 2 | S52: 1115174.8 | T52: Very High Risk | AM52: LN10562 | AN52: Rani Malhotra | AO52: 25 | AP52: Business Owner | AQ52: 248061 | AR52: 200000 | AS52: 48 | AT52: 10.15 | AU52: Agriculture | AV52: 302 | AW52: 44288 | AX52: 2021-04-18 | AY52: Rejected | AZ52: 5086.94 | BA52: North | BB52: Chandigarh-Main | BC52: Defaulted | BD52: 5 | BE52: 181687.02
A53: LN10924 | B53: Madhuri Banerjee | C53: 23 | D53: Self-Employed | E53: 217401 | F53: 2000000 | G53: 24 | H53: 20.13 | I53: Medical | J53: 669 | K53: 45156 | L53: 2023-08-28 | M53: Approved | N53: 101918.66 | O53: West | P53: Mumbai-Bandra | Q53: On Track | R53: 0 | S53: 1082732.1 | T53: Medium Risk | AM53: LN10202 | AN53: Rekha Kapoor | AO53: 39 | AP53: Business Owner | AQ53: 232145 | AR53: 200000 | AS53: 84 | AT53: 15.44 | AU53: Education | AV53: 879 | AW53: 44291 | AX53: 2021-04-11 | AY53: Approved | AZ53: 3908.89 | BA53: West | BB53: Pune-Shivajinagar | BC53: Defaulted | BD53: 10 | BE53: 178891.99
A54: LN10604 | B54: Komal Mehta | C54: 47 | D54: Self-Employed | E54: 74487 | F54: 1500000 | G54: 48 | H54: 14.38 | I54: Agriculture | J54: 772 | K54: 45075 | L54: 2023-06-25 | M54: Approved | N54: 41276.22 | O54: East | P54: Kolkata-Park Street | Q54: On Track | R54: 1 | S54: 1054216.8 | T54: Low Risk | AM54: LN10926 | AN54: Sunita Reddy | AO54: 54 | AP54: Business Owner | AQ54: 19247 | AR54: 750000 | AS54: 120 | AT54: 21.94 | AU54: Medical | AV54: 851 | AW54: 44334 | AX54: 2021-06-13 | AZ54: 15471.64 | BA54: West | BB54: Pune-Shivajinagar | BC54: Defaulted | BD54: 9 | BE54: 165172.01
A55: LN10807 | B55: Naveen Kulkarni | C55: 38 | D55: Government Employee | E55: 71765 | F55: 2000000 | G55: 12 | H55: 12.44 | I55: Debt Consolidation | J55: 737 | K55: 44785 | L55: 2022-09-11 | M55: Approved | N55: 178109.51 | O55: North | P55: Delhi-Connaught | Q55: On Track | R55: 2 | S55: 1038208.7 | T55: Medium Risk | AM55: LN11077 | AN55: Pooja Yadav | AO55: 56 | AP55: Business Owner | AQ55: 53362 | AR55: 200000 | AS55: 24 | AT55: 11.16 | AU55: Debt Consolidation | AV55: 863 | AW55: 44718 | AX55: 2022-06-24 | AY55: Approved | AZ55: 9336.43 | BA55: West | BB55: Mumbai-Andheri | BC55: Defaulted | BD55: 1 | BE55: 149583.28
A56: LN11015 | B56: Ravi Mehta | C56: 56 | D56: Government Employee | E56: 64635 | F56: 1500000 | G56: 24 | H56: 17.69 | I56: Vehicle Loan | J56: Not Available | K56: 44529 | L56: 2021-12-14 | M56: Approved | N56: 74661.67 | O56: South | P56: Chennai-Adyar | Q56: Late | R56: 12 | S56: 1029631.5 | T56: Unclassified | AM56: LN10254 | AN56: Sarala Jain | AO56: 44 | AP56: Self-Employed | AQ56: 234585 | AR56: 200000 | AS56: 24 | AT56: 11.63 | AU56: Debt Consolidation | AV56: 350 | AW56: 44650 | AX56: 2022-04-22 | AY56: Rejected | AZ56: 9380.17 | BA56: South | BB56: Kochi-MG Road | BC56: Defaulted | BD56: 12 | BE56: 149347.08
A57: LN10267 | B57: Priya Gupta | C57: 29 | D57: Business Owner | F57: 1000000 | G57: 12 | H57: 12.94 | I57: Business Expansion | J57: 847 | K57: 44418 | L57: 2021-09-02 | M57: Pending | N57: 89289.13 | O57: Central | P57: Indore-Main | Q57: Late | R57: 9 | S57: 1000000 | T57: Low Risk | AM57: LN10842 | AN57: Smita Pillai | AO57: 28 | AP57: Business Owner | AQ57: 186979 | AR57: 750000 | AS57: 180 | AT57: 12.96 | AU57: Debt Consolidation | AV57: 395 | AW57: 45186 | AX57: 2023-09-29 | AY57: Approved | AZ57: 9469.58 | BA57: South | BB57: Hyderabad-Hitech | BC57: Defaulted | BD57: 8 | BE57: 144893.84
A58: LN11047 | B58: Rohit Mehta | C58: 35 | D58: Salaried | E58: 119212 | F58: 1000000 | G58: 120 | H58: 7.93 | I58: Agriculture | J58: 742 | K58: 44287 | L58: 2021-04-25 | M58: Approved | N58: 12095.8 | O58: West | P58: Ahmedabad-Cg Road | Q58: Late | R58: 2 | S58: 989113.78 | T58: Medium Risk | AM58: LN10286 | AN58: Chetna Menon | AO58: 34 | AP58: Self-Employed | AQ58: 178621 | AR58: 1500000 | AS58: 60 | AT58: 17.46 | AU58: Education | AV58: 482 | AW58: 44857 | AX58: 2022-11-17 | AY58: Approved | AZ58: 37650.88 | BA58: Central | BB58: Lucknow-Hazratganj | BC58: Defaulted | BD58: 11 | BE58: 144568.32
A59: LN10672 | B59: Arjun Saxena | C59: 53 | D59: Government Employee | E59: 194600 | F59: 1000000 | G59: 240 | H59: 17.62 | I59: Debt Consolidation | J59: 314 | K59: 45067 | L59: 2023-06-15 | M59: Rejected | N59: 15141.3 | O59: Central | P59: Bhopal-Mp Nagar | Q59: Late | R59: 11 | S59: 986372.83 | T59: Very High Risk | U59: 6. Credit_Score has blank cells for some borrowers. Use an IF formula to fill these with the text Not Available, then paste the values back. | AM59: LN10698 | AN59: Vikram Tiwari | AO59: 37 | AP59: Freelancer | AQ59: 184114 | AR59: 300000 | AS59: 24 | AT59: 18 | AU59: Education | AV59: 312 | AW59: 44239 | AX59: 2021-02-18 | AY59: Approved | AZ59: 14977.23 | BA59: Central | BB59: Indore-Main | BC59: Defaulted | BD59: 6 | BE59: 138245.92
A60: LN10749 | B60: Divya Jain | C60: 37 | D60: Salaried | E60: 71409 | F60: 1000000 | G60: 84 | H60: 12.89 | I60: Medical | J60: 425 | K60: 44870 | L60: 2022-11-14 | M60: Approved | N60: 18132.21 | O60: North | P60: Noida-Sector18 | Q60: On Track | R60: 2 | S60: 983681.01 | T60: Very High Risk | AM60: LN10224 | AN60: Varsha Chatterjee | AO60: 60 | AP60: Salaried | AQ60: 71366 | AR60: 250000 | AS60: 36 | AT60: 8.82 | AU60: Personal | AV60: 664 | AW60: 44729 | AX60: 2022-07-16 | AY60: Pending | AZ60: 7929.01 | BA60: West | BB60: Surat-Ring Road | BC60: Defaulted | BD60: 0 | BE60: 114413.93
A61: LN10828 | B61: Arjun Yadav | C61: 40 | D61: Salaried | E61: 202760 | F61: 1500000 | G61: 24 | H61: 13.94 | I61: Debt Consolidation | J61: 805 | K61: 44435 | L61: 2021-09-10 | M61: Approved | N61: 71976.81 | O61: East | P61: Kolkata-Park Street | Q61: Closed | R61: 0 | S61: 981766.97 | T61: Low Risk | AM61: LN10193 | AN61: Meena Nayak | AO61: 48 | AP61: Government Employee | AQ61: 51141 | AR61: 750000 | AS61: 120 | AT61: 13.63 | AU61: Agriculture | AV61: 850 | AW61: 44788 | AX61: 2022-08-22 | AY61: Rejected | AZ61: 11478.71 | BA61: South | BB61: Kochi-MG Road | BC61: Defaulted | BD61: 2 | BE61: 109487.98
A62: LN10156 | B62: Harish Nayak | C62: 27 | D62: Government Employee | E62: 49862 | F62: 1000000 | G62: 84 | H62: 9.22 | I62: Debt Consolidation | J62: 841 | K62: 44808 | L62: 2022-09-21 | M62: Approved | N62: 16200.95 | O62: South | P62: Bangalore-Whitefield | Q62: On Track | R62: 0 | S62: 970838.29 | T62: Low Risk | AM62: LN10735 | AN62: Rani Singh | AO62: 64 | AP62: Business Owner | AQ62: 238269 | AR62: 300000 | AS62: 48 | AT62: 10.73 | AU62: Agriculture | AV62: 864 | AW62: 44451 | AX62: 2021-09-26 | AY62: Rejected | AZ62: 7714.38 | BA62: West | BB62: Mumbai-Andheri | BC62: Defaulted | BD62: 3 | BE62: 91711.74
A63: LN11097 | B63: Mohan Patel | C63: 35 | D63: Freelancer | E63: 218180 | F63: 1000000 | G63: 36 | H63: 14.02 | I63: Education | J63: 609 | K63: 44662 | L63: 2022-04-28 | M63: Approved | N63: 34187.34 | O63: West | P63: Mumbai-Bandra | Q63: Late | R63: 2 | S63: 969231.39 | T63: High Risk | AM63: LN10466 | AN63: Ashok Banerjee | AO63: 51 | AP63: Self-Employed | AQ63: 177170 | AR63: 100000 | AS63: 240 | AT63: 11.64 | AU63: Education | AV63: 457 | AW63: 44845 | AX63: 2022-11-01 | AY63: Approved | AZ63: 1076.09 | BA63: South | BB63: Bangalore-Whitefield | BC63: Defaulted | BD63: 1 | BE63: 90315.19
A64: LN10076 | B64: Anil Kaur | C64: 57 | D64: Business Owner | E64: 38672 | F64: 2000000 | G64: 120 | H64: 7.7 | I64: Vehicle Loan | J64: 765 | K64: 44957 | L64: 2023-02-06 | M64: Rejected | N64: 23949.64 | O64: East | P64: Bhubaneswar-Main | Q64: On Track | R64: 2 | S64: 965375.55 | T64: Low Risk | AM64: LN10969 | AN64: Kiran Patel | AO64: 57 | AP64: Freelancer | AQ64: 161537 | AR64: 1000000 | AS64: 12 | AT64: 20.49 | AU64: Agriculture | AV64: 451 | AW64: 44762 | AX64: 2022-08-10 | AY64: Approved | AZ64: 92869.18 | BA64: North | BB64: Noida-Sector18 | BC64: Defaulted | BD64: 1 | BE64: 80595.12
A65: LN10119 | B65: Sanjay Deshpande | C65: 28 | D65: Salaried | E65: 100962 | F65: 1000000 | G65: 60 | H65: 11.94 | I65: Debt Consolidation | J65: 470 | K65: 44919 | L65: 2023-01-15 | M65: Approved | N65: 22214.14 | O65: West | P65: Pune-Shivajinagar | Q65: On Track | R65: 1 | S65: 960014.55 | T65: Very High Risk | AM65: LN10991 | AN65: Harish Mehta | AO65: 40 | AP65: Government Employee | AQ65: 31685 | AR65: 150000 | AS65: 36 | AT65: 16.59 | AU65: Medical | AV65: 749 | AW65: 45279 | AX65: 2023-12-31 | AY65: Approved | AZ65: 5317.35 | BA65: North | BB65: Gurgaon-CyberCity | BC65: Defaulted | BD65: 1 | BE65: 78215.77
A66: LN10447 | B66: Abhishek Saxena | C66: 30 | D66: Self-Employed | E66: 52509 | F66: 1000000 | G66: 60 | H66: 15.08 | I66: Debt Consolidation | J66: 544 | K66: 44565 | L66: 2022-01-29 | M66: Rejected | N66: 23831.94 | O66: South | P66: Kochi-Mg Road | Q66: On Track | R66: 2 | S66: 957102.51 | T66: Very High Risk | AM66: LN11088 | AN66: Kiran Gupta | AO66: 36 | AP66: Government Employee | AQ66: 184085 | AR66: 500000 | AS66: 240 | AT66: 19.25 | AU66: Home Purchase | AV66: 690 | AW66: 44381 | AX66: 2021-07-29 | AY66: Approved | AZ66: 8200.76 | BA66: East | BB66: Kolkata-Park Street | BC66: Defaulted | BD66: 12 | BE66: 71920.33
A67: LN10106 | B67: Anil Joshi | C67: 31 | D67: Salaried | E67: 92540 | F67: 2000000 | G67: 24 | H67: 14.86 | I67: Home Purchase | J67: 644 | K67: 44512 | L67: 2021-11-20 | M67: Approved | N67: 96840.32 | O67: Central | P67: Bhopal-Mp Nagar | Q67: Late | R67: 9 | S67: 954124.54 | T67: High Risk | AM67: LN10369 | AN67: Lakshmi Jain | AO67: 49 | AP67: Freelancer | AQ67: 242496 | AR67: 75000 | AS67: 48 | AT67: 18.34 | AU67: Home Purchase | AV67: 691 | AW67: 44850 | AX67: 2022-11-05 | AY67: Approved | AZ67: 2216.47 | BA67: North | BB67: Noida-Sector18 | BC67: Defaulted | BD67: 8 | BE67: 71010.35
A68: LN11166 | B68: Bhavna Dubey | C68: 26 | D68: Freelancer | E68: 203984 | F68: 1000000 | G68: 240 | H68: 8.66 | I68: Medical | J68: 771 | K68: 44264 | L68: 2021-04-05 | M68: Approved | N68: 8779.76 | O68: South | P68: Chennai-Adyar | Q68: On Track | R68: 1 | S68: 944687.51 | T68: Low Risk | AM68: LN11106 | AN68: Siddharth Deshpande | AO68: 55 | AP68: Self-Employed | AQ68: 190047 | AR68: 1000000 | AS68: 240 | AT68: 17.4 | AU68: Personal | AV68: 531 | AW68: 44869 | AX68: 2022-11-23 | AY68: Rejected | AZ68: 14972.95 | BA68: North | BB68: Gurgaon-CyberCity | BC68: Defaulted | BD68: 7 | BE68: 70179.8
A69: LN10309 | B69: Rohit Saxena | C69: 44 | D69: Salaried | E69: 72362 | F69: 2000000 | G69: 180 | H69: 10.86 | I69: Business Expansion | J69: 678 | K69: 45257 | L69: 2023-12-25 | M69: Approved | N69: 22556.43 | O69: South | P69: Bangalore-Koramangala | Q69: On Track | R69: 2 | S69: 944359.08 | T69: Medium Risk | U69: 7. Application_Date has two different date formats in the same column. Use Text to Columns to fix the non-standard entries so all dates are consistent. | AM69: LN10364 | AN69: Siddharth Gupta | AO69: 56 | AP69: Government Employee | AQ69: 131132 | AR69: 250000 | AS69: 84 | AT69: 15.48 | AU69: Medical | AV69: 680 | AW69: 44689 | AX69: 2022-05-29 | AY69: Approved | AZ69: 4891.76 | BA69: West | BB69: Ahmedabad-CG Road | BC69: Defaulted | BD69: 11 | BE69: 69494.06
A70: LN11099 | B70: Geeta Reddy | C70: 44 | D70: Freelancer | E70: 116333 | F70: 1000000 | G70: 120 | H70: 8.63 | I70: Business Expansion | J70: 663 | K70: 45178 | L70: 2023-09-14 | M70: Approved | N70: 12468.2 | O70: Central | P70: Lucknow-Hazratganj | Q70: Closed | R70: 1 | S70: 943893.1 | T70: Medium Risk | AM70: LN10314 | AN70: Tarun Singh | AO70: 58 | AP70: Self-Employed | AQ70: 29656 | AR70: 100000 | AS70: 60 | AT70: 20.88 | AU70: Debt Consolidation | AV70: 877 | AW70: 45116 | AX70: 2023-07-31 | AY70: Approved | AZ70: 2698.59 | BA70: North | BB70: Noida-Sector18 | BC70: Defaulted | BD70: 1 | BE70: 68426.5
A71: LN10026 | B71: Suresh Jain | C71: 57 | D71: Freelancer | E71: 177702 | F71: 1500000 | G71: 36 | H71: 20.92 | I71: Personal | J71: 466 | K71: 44877 | L71: 2022-12-10 | M71: Pending | N71: 56451.01 | O71: South | P71: Hyderabad-Hitech | Q71: Defaulted | R71: 0 | S71: 941135 | T71: Very High Risk | AM71: LN10654 | AN71: Rani Reddy | AO71: 41 | AP71: Freelancer | AQ71: 186608 | AR71: 100000 | AS71: 36 | AT71: 13.91 | AU71: Agriculture | AV71: 598 | AW71: 44215 | AX71: 2021-02-02 | AY71: Approved | AZ71: 3413.39 | BA71: South | BB71: Bangalore-Whitefield | BC71: Defaulted | BD71: 3 | BE71: 63135.39
A72: LN10541 | B72: Usha Reddy | C72: 43 | D72: Salaried | E72: 41912 | F72: 1000000 | G72: 120 | H72: 21.7 | I72: Agriculture | J72: 892 | K72: 45195 | L72: 2023-10-11 | M72: Rejected | N72: 20465.82 | O72: Central | P72: Lucknow-Hazratganj | Q72: On Track | R72: 1 | S72: 926323.05 | T72: Low Risk | AM72: LN10583 | AN72: Deepa Patel | AO72: 36 | AP72: Freelancer | AQ72: 34514 | AR72: 150000 | AS72: 48 | AT72: 9.88 | AU72: Business Expansion | AV72: 364 | AW72: 44246 | AX72: 2021-03-12 | AY72: Approved | AZ72: 3795.75 | BA72: North | BB72: Delhi-Connaught | BC72: Defaulted | BD72: 7 | BE72: 57763.27
A73: LN10665 | B73: Abhishek Pillai | C73: 45 | D73: Government Employee | E73: 187311 | F73: 1000000 | G73: 240 | H73: 16.27 | I73: Debt Consolidation | J73: 457 | K73: 44703 | L73: 2022-05-27 | M73: Approved | N73: 14115.52 | O73: East | P73: Patna-Boring Road | Q73: On Track | R73: 1 | S73: 923776.19 | T73: Very High Risk | AM73: LN10362 | AN73: Vikram Chatterjee | AO73: 26 | AP73: Self-Employed | AQ73: 151179 | AR73: 75000 | AS73: 24 | AT73: 18.01 | AU73: Debt Consolidation | AV73: 494 | AW73: 44563 | AX73: 2022-01-22 | AY73: Approved | AZ73: 3744.67 | BA73: South | BB73: Kochi-MG Road | BC73: Defaulted | BD73: 10 | BE73: 51408.58
A74: LN10734 | B74: Bhavna Iyer | C74: 27 | D74: Salaried | E74: 38498 | F74: 1000000 | G74: 12 | H74: 16.44 | I74: Debt Consolidation | J74: 406 | K74: 45106 | L74: 2023-07-18 | M74: Pending | N74: 90939.21 | O74: West | P74: Surat-Ring Road | Q74: On Track | R74: 2 | S74: 918154.71 | T74: Very High Risk | AM74: LN10903 | AN74: Ganesh Menon | AO74: 38 | AP74: Salaried | AQ74: 101514 | AR74: 1000000 | AS74: 24 | AT74: 14.14 | AU74: Agriculture | AV74: Not Available | AW74: 45107 | AX74: 2023-07-13 | AY74: Approved | AZ74: 48079.05 | BA74: East | BB74: Bhubaneswar-Main | BC74: Defaulted | BD74: 4 | BE74: 48034.81
A75: LN10723 | B75: Varsha Malhotra | C75: 54 | D75: Freelancer | E75: 83898 | F75: 1000000 | G75: 12 | H75: 16.5 | I75: Home Purchase | J75: 550 | K75: 44792 | L75: 2022-09-03 | M75: Rejected | N75: 90967.64 | O75: Central | P75: Indore-Main | Q75: On Track | R75: 0 | S75: 918129.12 | T75: High Risk | AM75: LN10133 | AN75: Sunil Yadav | AO75: 53 | AP75: Business Owner | AQ75: 145382 | AR75: 50000 | AS75: 24 | AT75: 21.21 | AU75: Agriculture | AV75: 546 | AW75: 44300 | AX75: 2021-04-26 | AY75: Rejected | AZ75: 2574.44 | BA75: South | BB75: Kochi-MG Road | BC75: Defaulted | BD75: 5 | BE75: 47683
A76: LN11118 | B76: Jyoti Yadav | C76: 64 | D76: Freelancer | E76: 220448 | F76: 1500000 | G76: 84 | H76: 14.02 | I76: Medical | J76: 732 | K76: 44212 | L76: 2021-02-15 | M76: Approved | N76: 28126.59 | O76: East | P76: Guwahati-Main | Q76: Late | R76: 11 | S76: 917779.59 | T76: Medium Risk | AM76: LN10057 | AN76: Kavitha Chaudhary | AO76: 63 | AP76: Self-Employed | AQ76: 84633 | AR76: 100000 | AS76: 24 | AT76: 8.36 | AU76: Business Expansion | AV76: 882 | AW76: 44819 | AX76: 2022-10-10 | AY76: Pending | AZ76: 4539.17 | BA76: East | BB76: Patna-Boring Road | BC76: Defaulted | BD76: 1 | BE76: 42806.46
A77: LN11037 | B77: Arjun Deshpande | C77: 42 | D77: Freelancer | E77: 213171 | F77: 1000000 | G77: 120 | H77: 7.78 | I77: Business Expansion | J77: 804 | K77: 44279 | L77: 2021-04-02 | M77: Approved | N77: 12016.82 | O77: North | P77: Gurgaon-Cybercity | Q77: Closed | R77: 2 | S77: 913478.9 | T77: Low Risk | AM77: LN10878 | AN77: Komal Chaudhary | AO77: 30 | AP77: Freelancer | AQ77: 64275 | AR77: 50000 | AS77: 48 | AT77: 11.88 | AU77: Vehicle Loan | AV77: 647 | AW77: 44780 | AX77: 2022-08-19 | AY77: Pending | AZ77: 1313.75 | BA77: West | BB77: Mumbai-Bandra | BC77: Defaulted | BD77: 6 | BE77: 39358.62
A78: LN10179 | B78: Sarala Verma | C78: 58 | D78: Government Employee | E78: 59455 | F78: 1000000 | G78: 120 | H78: 9.96 | I78: Business Expansion | J78: 608 | K78: 44539 | L78: 2021-12-25 | M78: Approved | N78: 13192.93 | O78: East | P78: Patna-Boring Road | Q78: Late | R78: 2 | S78: 905010.9 | T78: High Risk | AM78: LN10554 | AN78: Komal Kaur | AO78: 34 | AP78: Business Owner | AQ78: 37093 | AR78: 50000 | AS78: 240 | AT78: 12.35 | AU78: Education | AV78: Not Available | AW78: 45244 | AX78: 2023-12-04 | AY78: Approved | AZ78: 562.79 | BA78: Central | BB78: Nagpur-Dharampeth | BC78: Defaulted | BD78: 3 | BE78: 38350.25
A79: LN10771 | B79: Tarun Dubey | C79: 55 | D79: Self-Employed | E79: 84549 | F79: 1000000 | G79: 84 | H79: 20.38 | I79: Debt Consolidation | J79: 727 | K79: 45262 | L79: 2023-12-27 | M79: Approved | N79: 22435.57 | O79: East | P79: Bhubaneswar-Main | Q79: On Track | R79: 0 | S79: 899039.94 | T79: Medium Risk | AM79: LN10136 | AN79: Geeta Mehta | AO79: 34 | AP79: Government Employee | AQ79: 148463 | AR79: 300000 | AS79: 240 | AT79: 8.08 | AU79: Home Purchase | AV79: Not Available | AW79: 44502 | AX79: 2021-11-24 | AY79: Rejected | AZ79: 2524.28 | BA79: East | BB79: Patna-Boring Road | BC79: Defaulted | BD79: 8 | BE79: 36465.17
A80: LN10087 | B80: Manoj Iyer | C80: 42 | D80: Freelancer | E80: 96926 | F80: 1000000 | G80: 60 | H80: 12.93 | I80: Education | J80: 785 | K80: 45081 | L80: 2023-06-10 | M80: Approved | N80: 22717.26 | O80: North | P80: Delhi-Connaught | Q80: On Track | R80: 0 | S80: 897772.33 | T80: Low Risk | AM80: LN10310 | AN80: Geeta Nayak | AO80: 52 | AP80: Freelancer | AQ80: 246093 | AR80: 50000 | AS80: 12 | AT80: 21.72 | AU80: Medical | AV80: 405 | AW80: 44553 | AX80: 2022-01-07 | AY80: Rejected | AZ80: 4672.98 | BA80: Central | BB80: Nagpur-Dharampeth | BC80: Defaulted | BD80: 11 | BE80: 33177.27
A81: LN10692 | B81: Abhishek Sharma | C81: 54 | D81: Freelancer | E81: 147072 | F81: 1500000 | G81: 240 | H81: 11.25 | I81: Personal | J81: 603 | K81: 44655 | L81: 2022-04-08 | M81: Pending | N81: 15738.84 | O81: East | P81: Guwahati-Main | Q81: On Track | R81: 0 | S81: 890906.89 | T81: High Risk | AM81: LN10664 | AN81: Ravi Das | AO81: 46 | AP81: Self-Employed | AQ81: 119873 | AR81: 400000 | AS81: 24 | AT81: 21.2 | AU81: Debt Consolidation | AV81: 446 | AW81: 44748 | AX81: 2022-07-29 | AY81: Approved | AZ81: 20593.58 | BA81: Central | BB81: Bhopal-MP Nagar | BC81: Defaulted | BD81: 1 | BE81: 29315.56
A82: LN11001 | B82: Jyoti Deshpande | C82: 61 | D82: Government Employee | E82: 154090 | F82: 1500000 | G82: 12 | H82: 17.3 | I82: Vehicle Loan | J82: 387 | K82: 44381 | L82: 2021-07-17 | M82: Approved | N82: 137020.77 | O82: North | P82: Delhi-Connaught | Q82: On Track | R82: 0 | S82: 883406.54 | T82: Very High Risk | AM82: LN10950 | AN82: Vikram Das | AO82: 57 | AP82: Business Owner | AQ82: 69723 | AR82: 1500000 | AS82: 24 | AT82: 8.36 | AU82: Debt Consolidation | AV82: 443 | AW82: 44693 | AX82: 2022-05-27 | AY82: Approved | AZ82: 68087.49 | BA82: South | BB82: Hyderabad-Hitech | BC82: Defaulted | BD82: 2 | BE82: 29310.22
A83: LN10243 | B83: Usha Saxena | C83: 53 | D83: Business Owner | E83: 38890 | F83: 1000000 | G83: 240 | H83: 13.12 | I83: Medical | J83: 690 | K83: 44736 | L83: 2022-07-11 | M83: Approved | N83: 11801.35 | O83: East | P83: Kolkata-Salt Lake | Q83: Closed | R83: 1 | S83: 883166.64 | T83: Medium Risk | AM83: LN10200 | AN83: Pallavi Deshpande | AO83: 37 | AP83: Freelancer | AQ83: 143308 | AR83: 100000 | AS83: 60 | AT83: 16.6 | AU83: Debt Consolidation | AV83: 762 | AW83: 44766 | AX83: 2022-08-18 | AY83: Rejected | AZ83: 2463.8 | BA83: North | BB83: Delhi-Connaught | BC83: Defaulted | BD83: 6 | BE83: 29042.56
A84: LN10275 | B84: Bhavna Nayak | C84: 44 | D84: Government Employee | E84: 22554 | F84: 1000000 | G84: 36 | H84: 14.5 | I84: Agriculture | J84: 415 | K84: 44732 | L84: 2022-07-13 | M84: Approved | N84: 34420.98 | O84: West | P84: Ahmedabad-Cg Road | Q84: Defaulted | R84: 0 | S84: 876084.47 | T84: Very High Risk | AM84: LN11075 | AN84: Lakshmi Malhotra | AO84: 39 | AP84: Business Owner | AQ84: 171699 | AR84: 300000 | AS84: 48 | AT84: 18.64 | AU84: Education | AV84: 602 | AW84: 44854 | AX84: 2022-10-29 | AY84: Approved | AZ84: 8913.14 | BA84: South | BB84: Chennai-Adyar | BC84: Defaulted | BD84: 11 | BE84: 27257.92
A85: LN10183 | B85: Kavitha Pillai | C85: 59 | D85: Government Employee | E85: 62166 | F85: 1000000 | G85: 240 | H85: 7.89 | I85: Agriculture | J85: 514 | K85: 45034 | L85: 2023-05-12 | M85: Pending | N85: 8296.07 | O85: West | P85: Pune-Shivajinagar | Q85: On Track | R85: 2 | S85: 873070.13 | T85: Very High Risk | AM85: LN10886 | AN85: Rohit Iyer | AO85: 46 | AP85: Government Employee | AQ85: 205159 | AR85: 75000 | AS85: 84 | AT85: 20.95 | AU85: Business Expansion | AV85: 732 | AW85: 44359 | AX85: 2021-07-11 | AY85: Approved | AZ85: 1708.63 | BA85: West | BB85: Mumbai-Andheri | BC85: Defaulted | BD85: 2 | BE85: 25791.46
A86: LN10440 | B86: Amit Nayak | C86: 64 | D86: Self-Employed | E86: 93347 | F86: 1500000 | G86: 120 | H86: 20.5 | I86: Medical | J86: 798 | K86: 44483 | L86: 2021-10-18 | M86: Approved | N86: 29487.35 | O86: North | P86: Gurgaon-Cybercity | Q86: On Track | R86: 2 | S86: 863073.24 | T86: Low Risk | AM86: LN10195 | AN86: Jyoti Malhotra | AO86: 50 | AP86: Freelancer | AQ86: 58844 | AR86: 75000 | AS86: 12 | AT86: 19.04 | AU86: Personal | AV86: 599 | AW86: 44788 | AX86: 2022-08-23 | AY86: Rejected | AZ86: 6913.18 | BA86: North | BB86: Noida-Sector18 | BC86: Defaulted | BD86: 3 | BE86: 25225.1
A87: LN11059 | B87: Ravi Nair | C87: 27 | D87: Self-Employed | E87: 204865 | F87: 1500000 | G87: 24 | H87: 14.09 | I87: Medical | J87: 547 | K87: 44831 | L87: 2022-10-17 | M87: Approved | N87: 72083.12 | O87: Central | P87: Raipur-Main | Q87: Late | R87: 0 | S87: 851251.92 | T87: Very High Risk | AM87: LN10906 | AN87: Anil Patel | AO87: 35 | AP87: Government Employee | AQ87: 94418 | AR87: 100000 | AS87: 12 | AT87: 11.26 | AU87: Debt Consolidation | AV87: 788 | AW87: 44516 | AX87: 2021-12-07 | AY87: Approved | AZ87: 8850.3 | BA87: Central | BB87: Bhopal-MP Nagar | BC87: Defaulted | BD87: 5 | BE87: 20347.3
A88: LN10993 | B88: Vinod Shetty | C88: 24 | D88: Self-Employed | E88: 42208 | F88: 1000000 | G88: 48 | H88: 7.59 | I88: Home Purchase | J88: 876 | K88: 44656 | L88: 2022-05-02 | M88: Approved | N88: 24220.93 | O88: North | P88: Gurgaon-Cybercity | Q88: On Track | R88: 2 | S88: 847408.14 | T88: Low Risk | AM88: LN11094 | AN88: Kavitha Verma | AO88: 32 | AP88: Government Employee | AQ88: 212791 | AR88: 50000 | AS88: 24 | AT88: 21.75 | AU88: Education | AV88: 300 | AW88: 45005 | AX88: 2023-04-09 | AY88: Rejected | AZ88: 2587.74 | BA88: East | BB88: Patna-Boring Road | BC88: Defaulted | BD88: 8 | BE88: 15065.51
A89: LN10104 | B89: Ravi Mehta | C89: 43 | D89: Salaried | E89: 167761 | F89: 1000000 | G89: 36 | H89: 20.79 | I89: Business Expansion | J89: Not Available | K89: 44831 | L89: 2022-10-17 | M89: Approved | N89: 37567.33 | O89: South | P89: Kochi-Mg Road | Q89: Late | R89: 11 | S89: 830947.02 | T89: Unclassified | AM89: LN10823 | AN89: Anita Banerjee | AO89: 52 | AP89: Self-Employed | AQ89: 207267 | AR89: 100000 | AS89: 240 | AT89: 8.71 | AU89: Home Purchase | AV89: 678 | AW89: 44558 | AX89: 2022-01-16 | AY89: Approved | AZ89: 881.16 | BA89: West | BB89: Ahmedabad-CG Road | BC89: Defaulted | BD89: 5 | BE89: 11179.07
A90: LN10204 | B90: Geeta Das | C90: 27 | D90: Business Owner | E90: 189196 | F90: 1000000 | G90: 36 | H90: 8.25 | I90: Business Expansion | J90: 539 | K90: 44199 | L90: 2021-01-12 | M90: Approved | N90: 31451.82 | O90: West | P90: Mumbai-Andheri | Q90: On Track | R90: 2 | S90: 830160.17 | T90: Very High Risk | AM90: LN10013 | AN90: Komal Shetty | AO90: 50 | AP90: Government Employee | AQ90: 133354 | AR90: 75000 | AS90: 48 | AT90: 10.76 | AU90: Medical | AV90: 321 | AW90: 44648 | AX90: 2022-03-31 | AY90: Approved | AZ90: 1929.68 | BA90: Central | BB90: Lucknow-Hazratganj | BC90: Defaulted | BD90: 3 | BE90: 10741.66
A91: LN10494 | B91: Ravi Kulkarni | C91: 56 | D91: Government Employee | E91: 19632 | F91: 2000000 | G91: 12 | H91: 21.87 | I91: Vehicle Loan | J91: 692 | K91: 45138 | L91: 2023-08-04 | M91: Approved | N91: 187063.65 | O91: West | P91: Pune-Shivajinagar | Q91: On Track | R91: 1 | S91: 821499 | T91: Medium Risk | AM91: LN10837 | AN91: Bhavna Kulkarni | AO91: 30 | AP91: Government Employee | AQ91: 156496 | AR91: 50000 | AS91: 12 | AT91: 19.13 | AU91: Vehicle Loan | AV91: 641 | AW91: 44297 | AX91: 2021-04-30 | AY91: Rejected | AZ91: 4610.93 | BA91: East | BB91: Guwahati-Main | BC91: Defaulted | BD91: 1 | BE91: 8501.63
A92: LN10131 | B92: Pallavi Deshpande | C92: 44 | D92: Freelancer | E92: 49279 | F92: 2000000 | G92: 84 | H92: 14.97 | I92: Vehicle Loan | J92: 626 | K92: 45117 | L92: 2023-07-20 | M92: Approved | N92: 38559.85 | O92: South | P92: Hyderabad-Hitech | Q92: Grace Period | R92: 0 | S92: 820068.59 | T92: High Risk | AM92: LN11190 | AN92: Priya Singh | AO92: 34 | AP92: Salaried | AQ92: 151382 | AR92: 150000 | AS92: 84 | AT92: 13.16 | AU92: Vehicle Loan | AV92: 327 | AW92: 44345 | AX92: 2021-06-11 | AY92: Approved | AZ92: 2741.86 | BA92: West | BB92: Mumbai-Bandra | BC92: Defaulted | BD92: 10 | BE92: 6874.91
A93: LN10259 | B93: Manoj Kaur | C93: 46 | D93: Salaried | E93: 167836 | F93: 1500000 | G93: 48 | H93: 12.48 | I93: Personal | J93: 847 | K93: 44545 | L93: 2022-01-13 | M93: Approved | N93: 39855.19 | O93: West | P93: Pune-Shivajinagar | Q93: Defaulted | R93: 8 | S93: 818476.25 | T93: Low Risk | AM93: LN10219 | AN93: Jyoti Pillai | AO93: 56 | AP93: Self-Employed | AQ93: 54470 | AR93: 50000 | AS93: 120 | AT93: 7.85 | AU93: Medical | AV93: 309 | AW93: 44967 | AX93: 2023-03-12 | AY93: Approved | AZ93: 602.68 | BA93: East | BB93: Kolkata-Park Street | BC93: Defaulted | BD93: 12 | BE93: 4437.39
A94: LN10574 | B94: Chetna Kumar | C94: 41 | D94: Salaried | E94: 118626 | F94: 1500000 | G94: 24 | H94: 19.54 | I94: Business Expansion | J94: Not Available | K94: 44898 | L94: 2022-12-26 | M94: Rejected | N94: 76007.05 | O94: South | P94: Kochi-Mg Road | Q94: Late | R94: 8 | S94: 815936.55 | T94: Unclassified | AM94: LN10631 | AN94: Pallavi Saxena | AO94: 34 | AP94: Self-Employed | AQ94: 64709 | AR94: 50000 | AS94: 12 | AT94: 19.99 | AU94: Medical | AV94: 803 | AW94: 44961 | AX94: 2023-02-19 | AY94: Approved | AZ94: 4631.49 | BA94: West | BB94: Ahmedabad-CG Road | BC94: Defaulted | BD94: 6 | BE94: 4148.25
A95: LN10983 | B95: Mohan Jain | C95: 56 | D95: Salaried | E95: 230940 | F95: 1000000 | G95: 120 | H95: 18.21 | I95: Education | J95: 820 | K95: 45133 | L95: 2023-08-03 | M95: Approved | N95: 18153.94 | O95: East | P95: Kolkata-Park Street | Q95: Late | R95: 3 | S95: 803937.45 | T95: Low Risk | AM95: LN11004 | AN95: Shweta Rao | AO95: 64 | AP95: Self-Employed | AQ95: 131628 | AR95: 75000 | AS95: 12 | AT95: 9.47 | AU95: Debt Consolidation | AV95: 784 | AW95: 44237 | AX95: 2021-03-03 | AY95: Approved | AZ95: 6575.22 | BA95: West | BB95: Ahmedabad-CG Road | BC95: Defaulted | BD95: 2 | BE95: 3987.62
A96: LN10515 | B96: Komal Shah | C96: 62 | D96: Freelancer | E96: 222360 | F96: 1000000 | G96: 36 | H96: 7.54 | I96: Personal | J96: 612 | K96: 44520 | L96: 2021-11-30 | M96: Approved | N96: 31124.59 | O96: East | P96: Guwahati-Main | Q96: Defaulted | R96: 1 | S96: 803915.08 | T96: High Risk | AM96: LN10018 | AN96: Smita Banerjee | AO96: 49 | AP96: Government Employee | AQ96: 188505 | AR96: 1500000 | AS96: 180 | AT96: 9.74 | AU96: Business Expansion | AV96: 522 | AW96: 44321 | AX96: 2021-05-31 | AY96: Pending | AZ96: 15881.33 | BA96: North | BB96: Chandigarh-Main | BC96: Defaulted | BD96: 11 | BE96: 0
A97: LN10845 | B97: Meena Kaur | C97: 61 | D97: Freelancer | E97: 152207 | F97: 1500000 | G97: 48 | H97: 8.35 | I97: Agriculture | J97: 558 | K97: 44505 | L97: 2021-11-09 | M97: Approved | N97: 36866.32 | O97: West | P97: Pune-Shivajinagar | Q97: Defaulted | R97: 11 | S97: 803226.55 | T97: High Risk | AM97: LN10037 | AN97: Tarun Mishra | AO97: 55 | AP97: Freelancer | AQ97: 179298 | AR97: 150000 | AS97: 60 | AT97: 13.88 | AU97: Business Expansion | AV97: 540 | AW97: 44362 | AX97: 2021-06-22 | AY97: Approved | AZ97: 3480.91 | BA97: East | BB97: Bhubaneswar-Main | BC97: Defaulted | BD97: 5 | BE97: 0
A98: LN10047 | B98: Shweta Nair | C98: 39 | D98: Freelancer | E98: 78927 | F98: 2000000 | G98: 180 | H98: 15.76 | I98: Debt Consolidation | J98: 644 | K98: 45195 | L98: 2023-10-05 | M98: Rejected | N98: 29040.04 | O98: North | P98: Gurgaon-Cybercity | Q98: Late | R98: 5 | S98: 797742.34 | T98: High Risk | AM98: LN10079 | AN98: Chetna Mehta | AO98: 48 | AP98: Salaried | AQ98: 233547 | AR98: 400000 | AS98: 120 | AT98: 21.12 | AU98: Business Expansion | AV98: 333 | AW98: 44680 | AX98: 2022-05-29 | AY98: Approved | AZ98: 8029.55 | BA98: East | BB98: Kolkata-Salt Lake | BC98: Defaulted | BD98: 7 | BE98: 0
A99: LN11154 | B99: Chetna Kumar | C99: 28 | D99: Government Employee | E99: 130679 | F99: 1500000 | G99: 36 | H99: 10.7 | I99: Personal | J99: 523 | K99: 44220 | L99: 2021-02-14 | M99: Approved | N99: 48895.25 | O99: East | P99: Kolkata-Park Street | Q99: Late | R99: 0 | S99: 795908.4 | T99: Very High Risk | AM99: LN10083 | AN99: Divya Das | AO99: 25 | AP99: Self-Employed | AQ99: 209436 | AR99: 300000 | AS99: 240 | AT99: 9.15 | AU99: Vehicle Loan | AV99: 787 | AW99: 44420 | AX99: 2021-08-29 | AY99: Approved | AZ99: 2728.19 | BA99: West | BB99: Pune-Shivajinagar | BC99: Defaulted | BD99: 8 | BE99: 0
A100: LN10027 | B100: Manoj Verma | C100: 39 | D100: Self-Employed | E100: 221405 | F100: 1500000 | G100: 24 | H100: 13.05 | I100: Home Purchase | J100: 781 | K100: 44822 | L100: 2022-10-17 | M100: Pending | N100: 71347.97 | O100: South | P100: Bangalore-Whitefield | Q100: Closed | R100: 1 | S100: 793655.1 | T100: Low Risk | AM100: LN10109 | AN100: Komal Saxena | AO100: 45 | AP100: Government Employee | AQ100: 41893 | AR100: 1500000 | AS100: 240 | AT100: 19.84 | AU100: Business Expansion | AV100: 385 | AW100: 45248 | AX100: 2023-11-25 | AZ100: 25294.12 | BA100: South | BB100: Chennai-Adyar | BC100: Defaulted | BD100: 7 | BE100: 0
...

Sheet Reference_Tables
A1: RISK BAND MAPPING TABLE
A2: Credit Score Range | B2: Risk Category | C2: Risk Code | D2: Action Required
A3: 750 – 900 | B3: Low Risk | C3: LR | D3: Approve – Standard Terms
A4: 650 – 749 | B4: Medium Risk | C4: MR | D4: Approve – With Conditions
A5: 550 – 649 | B5: High Risk | C5: HR | D5: Review – Senior Approval
A6: 300 – 549 | B6: Very High Risk | C6: VHR | D6: Reject or Collateral Required
A7: Not Available | B7: Unclassified | C7: UC | D7: Pending Review
A10: BRANCH CODE REFERENCE TABLE
A11: Branch_Name | B11: Branch_Code | C11: Region | D11: Manager
A12: Delhi-Connaught | B12: BR-DL01 | C12: North | D12: Ananya Sharma
A13: Delhi-Dwarka | B13: BR-DL02 | C13: North | D13: Vikram Malhotra
A14: Noida-Sector18 | B14: BR-NR01 | C14: North | D14: Priyanka Gupta
A15: Gurgaon-CyberCity | B15: BR-GR01 | C15: North | D15: Rahul Kapoor
A16: Chandigarh-Main | B16: BR-CH01 | C16: North | D16: Deepak Nair
A17: Bangalore-Koramangala | B17: BR-BL01 | C17: South | D17: Santhosh Rao
A18: Bangalore-Whitefield | B18: BR-BL02 | C18: South | D18: Meena Iyer
A19: Chennai-Adyar | B19: BR-CH01 | C19: South | D19: Arvind Pillai
A20: Hyderabad-Hitech | B20: BR-HY01 | C20: South | D20: Lakshmi Reddy
A21: Kochi-MG Road | B21: BR-KC01 | C21: South | D21: Suresh Menon
A22: Kolkata-Park Street | B22: BR-KO01 | C22: East | D22: Debashis Das
... A36: Lucknow-Hazratganj | B36: BR-LK01 | C36: Central | D36: Sandeep Saxena

Sheet Task_Workspace
A1: TASK WORKSPACE – Students will work here | B1: Days to Approval | C1: Loan Age in Months | D1: Maturity Date | E1: Is_Matured | F1: DTI Ratio | G1: DTI Flag | H1: Risk Category | I1: Risk Code | J1: Branch Manager
B2: =DATEDIF(Loan_Data!K:K,Loan_Data!L:L,"D") -> 5 | C2: =DATEDIF(LoanData[[#This Row],[Approval_Date]],TODAY(),"M") -> 45 | D2: =EDATE(LoanData[[#This Row],[Approval_Date]],LoanData[[#This Row],[Loan_Term_Months]]) -> 46325 | E2: =IF(D2<TODAY(),"YES","NO") -> NO | F2: =IFERROR(LoanData[[#This Row],[EMI]]/LoanData[[#This Row],[Monthly_Income]]*100," ") -> 400.24561 | G2: {=_xlfn.IFS(F2>40, "High DTI Risk",F2>=25, "Moderate DTI",F2<25, "Low DTI")} -> High DTI Risk | H2: {=_xlfn.IFS(AND(LoanData[[#This Row],[Credit_Score]]>=750,LoanData[[#This Row],[Credit_Score]]<=900),"Low Risk", AND(LoanData[[#This Row],[Credit_Score]]>=650,LoanData[[#This Row],[Credit_Score]]<=749),"Medium Risk", AND(LoanData[[#This Row],[Credit_Score]]>=550,LoanData[[#This Row],[Credit_Score]]<=649),"High Risk", AND(LoanData[[#This Row],[Credit_Score]]>=300,LoanData[[#This Row],[Credit_Score]]<=549),"Very High Risk", LoanData[[#This Row],[Credit_Score]]="Not Available","Unclassified")} -> Very High Risk | I2: =_xlfn.XLOOKUP(H2,Reference_Tables!$B$2:$B$7,Reference_Tables!$C$2:$C$7,,0,1) -> VHR | J2: =INDEX(Reference_Tables!$D$11:$D$36,MATCH(LoanData[[#This Row],[Branch]],Reference_Tables!$A$11:$A$36,0)) -> Meena Iyer
A3: Use this sheet for calculated columns, classifications, and formulas. | B3: =DATEDIF(Loan_Data!K:K,Loan_Data!L:L,"D") -> 18 | C3: =DATEDIF(LoanData[[#This Row],[Approval_Date]],TODAY(),"M") -> 58 | D3: =EDATE(LoanData[[#This Row],[Approval_Date]],LoanData[[#This Row],[Loan_Term_Months]]) -> 44850 | E3: =IF(D3<TODAY(),"YES","NO") -> YES | F3: =IFERROR(LoanData[[#This Row],[EMI]]/LoanData[[#This Row],[Monthly_Income]]*100," ") -> 103.71806 | G3: {=_xlfn.IFS(F3>40, "High DTI Risk",F3>=25, "Moderate DTI",F3<25, "Low DTI")} -> High DTI Risk | H3: {=_xlfn.IFS(AND(LoanData[[#This Row],[Credit_Score]]>=750,LoanData[[#This Row],[Credit_Score]]<=900),"Low Risk", AND(LoanData[[#This Row],[Credit_Score]]>=650,LoanData[[#This Row],[Credit_Score]]<=749),"Medium Risk", AND(LoanData[[#This Row],[Credit_Score]]>=550,LoanData[[#This Row],[Credit_Score]]<=649),"High Risk", AND(LoanData[[#This Row],[Credit_Score]]>=300,LoanData[[#This Row],[Credit_Score]]<=549),"Very High Risk", LoanData[[#This Row],[Credit_Score]]="Not Available","Unclassified")} -> Low Risk | I3: =_xlfn.XLOOKUP(H3,Reference_Tables!$B$2:$B$7,Reference_Tables!$C$2:$C$7,,0,1) -> LR | J3: =INDEX(Reference_Tables!$D$11:$D$36,MATCH(LoanData[[#This Row],[Branch]],Reference_Tables!$A$11:$A$36,0)) -> Ravi Verma
B4: =DATEDIF(Loan_Data!K:K,Loan_Data!L:L,"D") -> 30 | C4: =DATEDIF(LoanData[[#This Row],[Approval_Date]],TODAY(),"M") -> 63 | D4: =EDATE(LoanData[[#This Row],[Approval_Date]],LoanData[[#This Row],[Loan_Term_Months]]) -> 46143 | E4: =IF(D4<TODAY(),"YES","NO") -> YES | F4: =IFERROR(LoanData[[#This Row],[EMI]]/LoanData[[#This Row],[Monthly_Income]]*100," ") -> 59.30693 | G4: {=_xlfn.IFS(F4>40, "High DTI Risk",F4>=25, "Moderate DTI",F4<25, "Low DTI")} -> High DTI Risk | H4: {=_xlfn.IFS(AND(LoanData[[#This Row],[Credit_Score]]>=750,LoanData[[#This Row],[Credit_Score]]<=900),"Low Risk", AND(LoanData[[#This Row],[Credit_Score]]>=650,LoanData[[#This Row],[Credit_Score]]<=749),"Medium Risk", AND(LoanData[[#This Row],[Credit_Score]]>=550,LoanData[[#This Row],[Credit_Score]]<=649),"High Risk", AND(LoanData[[#This Row],[Credit_Score]]>=300,LoanData[[#This Row],[Credit_Score]]<=549),"Very High Risk", LoanData[[#This Row],[Credit_Score]]="Not Available","Unclassified")} -> Very High Risk | I4: =_xlfn.XLOOKUP(H4,Reference_Tables!$B$2:$B$7,Reference_Tables!$C$2:$C$7,,0,1) -> VHR | J4: =INDEX(Reference_Tables!$D$11:$D$36,MATCH(LoanData[[#This Row],[Branch]],Reference_Tables!$A$11:$A$36,0)) -> Lakshmi Reddy
B5: =DATEDIF(Loan_Data!K:K,Loan_Data!L:L,"D") -> 25 | C5: =DATEDIF(LoanData[[#This Row],[Approval_Date]],TODAY(),"M") -> 32 | D5: =EDATE(LoanData[[#This Row],[Approval_Date]],LoanData[[#This Row],[Loan_Term_Months]]) -> 48926 | E5: =IF(D5<TODAY(),"YES","NO") -> NO | F5: =IFERROR(LoanData[[#This Row],[EMI]]/LoanData[[#This Row],[Monthly_Income]]*100," ") -> 27.006131 | G5: {=_xlfn.IFS(F5>40, "High DTI Risk",F5>=25, "Moderate DTI",F5<25, "Low DTI")} -> Moderate DTI | H5: {=_xlfn.IFS(AND(LoanData[[#This Row],[Credit_Score]]>=750,LoanData[[#This Row],[Credit_Score]]<=900),"Low Risk", AND(LoanData[[#This Row],[Credit_Score]]>=650,LoanData[[#This Row],[Credit_Score]]<=749),"Medium Risk", AND(LoanData[[#This Row],[Credit_Score]]>=550,LoanData[[#This Row],[Credit_Score]]<=649),"High Risk", AND(LoanData[[#This Row],[Credit_Score]]>=300,LoanData[[#This Row],[Credit_Score]]<=549),"Very High Risk", LoanData[[#This Row],[Credit_Score]]="Not Available","Unclassified")} -> Low Risk | I5: =_xlfn.XLOOKUP(H5,Reference_Tables!$B$2:$B$7,Reference_Tables!$C$2:$C$7,,0,1) -> LR | J5: =INDEX(Reference_Tables!$D$11:$D$36,MATCH(LoanData[[#This Row],[Branch]],Reference_Tables!$A$11:$A$36,0)) -> Suman Tiwari
B6: =DATEDIF(Loan_Data!K:K,Loan_Data!L:L,"D") -> 8 | C6: =DATEDIF(LoanData[[#This Row],[Approval_Date]],TODAY(),"M") -> 35 | D6: =EDATE(LoanData[[#This Row],[Approval_Date]],LoanData[[#This Row],[Loan_Term_Months]]) -> 47002 | E6: =IF(D6<TODAY(),"YES","NO") -> NO | F6: =IFERROR(LoanData[[#This Row],[EMI]]/LoanData[[#This Row],[Monthly_Income]]*100," ") -> 53.810251 | G6: {=_xlfn.IFS(F6>40, "High DTI Risk",F6>=25, "Moderate DTI",F6<25, "Low DTI")} -> High DTI Risk | H6: {=_xlfn.IFS(AND(LoanData[[#This Row],[Credit_Score]]>=750,LoanData[[#This Row],[Credit_Score]]<=900),"Low Risk", AND(LoanData[[#This Row],[Credit_Score]]>=650,LoanData[[#This Row],[Credit_Score]]<=749),"Medium Risk", AND(LoanData[[#This Row],[Credit_Score]]>=550,LoanData[[#This Row],[Credit_Score]]<=649),"High Risk", AND(LoanData[[#This Row],[Credit_Score]]>=300,LoanData[[#This Row],[Credit_Score]]<=549),"Very High Risk", LoanData[[#This Row],[Credit_Score]]="Not Available","Unclassified")} -> Medium Risk | I6: =_xlfn.XLOOKUP(H6,Reference_Tables!$B$2:$B$7,Reference_Tables!$C$2:$C$7,,0,1) -> MR | J6: =INDEX(Reference_Tables!$D$11:$D$36,MATCH(LoanData[[#This Row],[Branch]],Reference_Tables!$A$11:$A$36,0)) -> Hetal Patel
B7: =DATEDIF(Loan_Data!K:K,Loan_Data!L:L,"D") -> 26 | C7: =DATEDIF(LoanData[[#This Row],[Approval_Date]],TODAY(),"M") -> 48 | D7: =EDATE(LoanData[[#This Row],[Approval_Date]],LoanData[[#This Row],[Loan_Term_Months]]) -> 45862 | E7: =IF(D7<TODAY(),"YES","NO") -> YES | F7: =IFERROR(LoanData[[#This Row],[EMI]]/LoanData[[#This Row],[Monthly_Income]]*100," ") -> 54.676318 | G7: {=_xlfn.IFS(F7>40, "High DTI Risk",F7>=25, "Moderate DTI",F7<25, "Low DTI")} -> High DTI Risk | H7: {=_xlfn.IFS(AND(LoanData[[#This Row],[Credit_Score]]>=750,LoanData[[#This Row],[Credit_Score]]<=900),"Low Risk", AND(LoanData[[#This Row],[Credit_Score]]>=650,LoanData[[#This Row],[Credit_Score]]<=749),"Medium Risk", AND(LoanData[[#This Row],[Credit_Score]]>=550,LoanData[[#This Row],[Credit_Score]]<=649),"High Risk", AND(LoanData[[#This Row],[Credit_Score]]>=300,LoanData[[#This Row],[Credit_Score]]<=549),"Very High Risk", LoanData[[#This Row],[Credit_Score]]="Not Available","Unclassified")} -> Very High Risk | I7: =_xlfn.XLOOKUP(H7,Reference_Tables!$B$2:$B$7,Reference_Tables!$C$2:$C$7,,0,1) -> VHR | J7: =INDEX(Reference_Tables!$D$11:$D$36,MATCH(LoanData[[#This Row],[Branch]],Reference_Tables!$A$11:$A$36,0)) -> Ananya Sharma
B8: =DATEDIF(Loan_Data!K:K,Loan_Data!L:L,"D") -> 21 | C8: =DATEDIF(LoanData[[#This Row],[Approval_Date]],TODAY(),"M") -> 32 | D8: =EDATE(LoanData[[#This Row],[Approval_Date]],LoanData[[#This Row],[Loan_Term_Months]]) -> 45615 | E8: =IF(D8<TODAY(),"YES","NO") -> YES | F8: =IFERROR(LoanData[[#This Row],[EMI]]/LoanData[[#This Row],[Monthly_Income]]*100," ") -> 99.388359 | G8: {=_xlfn.IFS(F8>40, "High DTI Risk",F8>=25, "Moderate DTI",F8<25, "Low DTI")} -> High DTI Risk | H8: {=_xlfn.IFS(AND(LoanData[[#This Row],[Credit_Score]]>=750,LoanData[[#This Row],[Credit_Score]]<=900),"Low Risk", AND(LoanData[[#This Row],[Credit_Score]]>=650,LoanData[[#This Row],[Credit_Score]]<=749),"Medium Risk", AND(LoanData[[#This Row],[Credit_Score]]>=550,LoanData[[#This Row],[Credit_Score]]<=649),"High Risk", AND(LoanData[[#This Row],[Credit_Score]]>=300,LoanData[[#This Row],[Credit_Score]]<=549),"Very High Risk", LoanData[[#This Row],[Credit_Score]]="Not Available","Unclassified")} -> Very High Risk | I8: =_xlfn.XLOOKUP(H8,Reference_Tables!$B$2:$B$7,Reference_Tables!$C$2:$C$7,,0,1) -> VHR | J8: =INDEX(Reference_Tables!$D$11:$D$36,MATCH(LoanData[[#This Row],[Branch]],Reference_Tables!$A$11:$A$36,0)) -> Sachin Deshpande
B9: =DATEDIF(Loan_Data!K:K,Loan_Data!L:L,"D") -> 11 | C9: =DATEDIF(LoanData[[#This Row],[Approval_Date]],TODAY(),"M") -> 51 | D9: =EDATE(LoanData[[#This Row],[Approval_Date]],LoanData[[#This Row],[Loan_Term_Months]]) -> 45794 | E9: =IF(D9<TODAY(),"YES","NO") -> YES | F9: =IFERROR(LoanData[[#This Row],[EMI]]/LoanData[[#This Row],[Monthly_Income]]*100," ") -> 76.483315 | G9: {=_xlfn.IFS(F9>40, "High DTI Risk",F9>=25, "Moderate DTI",F9<25, "Low DTI")} -> High DTI Risk | H9: {=_xlfn.IFS(AND(LoanData[[#This Row],[Credit_Score]]>=750,LoanData[[#This Row],[Credit_Score]]<=900),"Low Risk", AND(LoanData[[#This Row],[Credit_Score]]>=650,LoanData[[#This Row],[Credit_Score]]<=749),"Medium Risk", AND(LoanData[[#This Row],[Credit_Score]]>=550,LoanData[[#This Row],[Credit_Score]]<=649),"High Risk", AND(LoanData[[#This Row],[Credit_Score]]>=300,LoanData[[#This Row],[Credit_Score]]<=549),"Very High Risk", LoanData[[#This Row],[Credit_Score]]="Not Available","Unclassified")} -> High Risk | I9: =_xlfn.XLOOKUP(H9,Reference_Tables!$B$2:$B$7,Reference_Tables!$C$2:$C$7,,0,1) -> HR | J9: =INDEX(Reference_Tables!$D$11:$D$36,MATCH(LoanData[[#This Row],[Branch]],Reference_Tables!$A$11:$A$36,0)) -> Deepak Nair
B10: =DATEDIF(Loan_Data!K:K,Loan_Data!L:L,"D") -> 7 | C10: =DATEDIF(LoanData[[#This Row],[Approval_Date]],TODAY(),"M") -> 35 | D10: =EDATE(LoanData[[#This Row],[Approval_Date]],LoanData[[#This Row],[Loan_Term_Months]]) -> 47007 | E10: =IF(D10<TODAY(),"YES","NO") -> NO | F10: =IFERROR(LoanData[[#This Row],[EMI]]/LoanData[[#This Row],[Monthly_Income]]*100," ") -> 223.78086 | G10: {=_xlfn.IFS(F10>40, "High DTI Risk",F10>=25, "Moderate DTI",F10<25, "Low DTI")} -> High DTI Risk | H10: {=_xlfn.IFS(AND(LoanData[[#This Row],[Credit_Score]]>=750,LoanData[[#This Row],[Credit_Score]]<=900),"Low Risk", AND(LoanData[[#This Row],[Credit_Score]]>=650,LoanData[[#This Row],[Credit_Score]]<=749),"Medium Risk", AND(LoanData[[#This Row],[Credit_Score]]>=550,LoanData[[#This Row],[Credit_Score]]<=649),"High Risk", AND(LoanData[[#This Row],[Credit_Score]]>=300,LoanData[[#This Row],[Credit_Score]]<=549),"Very High Risk", LoanData[[#This Row],[Credit_Score]]="Not Available","Unclassified")} -> Very High Risk | I10: =_xlfn.XLOOKUP(H10,Reference_Tables!$B$2:$B$7,Reference_Tables!$C$2:$C$7,,0,1) -> VHR | J10: =INDEX(Reference_Tables!$D$11:$D$36,MATCH(LoanData[[#This Row],[Branch]],Reference_Tables!$A$11:$A$36,0)) -> Santhosh Rao
B11: =DATEDIF(Loan_Data!K:K,Loan_Data!L:L,"D") -> 8 | C11: =DATEDIF(LoanData[[#This Row],[Approval_Date]],TODAY(),"M") -> 33 | D11: =EDATE(LoanData[[#This Row],[Approval_Date]],LoanData[[#This Row],[Loan_Term_Months]]) -> 48873 | E11: =IF(D11<TODAY(),"YES","NO") -> NO | F11: =IFERROR(LoanData[[#This Row],[EMI]]/LoanData[[#This Row],[Monthly_Income]]*100," ") -> 14.528235 | G11: {=_xlfn.IFS(F11>40, "High DTI Risk",F11>=25, "Moderate DTI",F11<25, "Low DTI")} -> Low DTI | H11: {=_xlfn.IFS(AND(LoanData[[#This Row],[Credit_Score]]>=750,LoanData[[#This Row],[Credit_Score]]<=900),"Low Risk", AND(LoanData[[#This Row],[Credit_Score]]>=650,LoanData[[#This Row],[Credit_Score]]<=749),"Medium Risk", AND(LoanData[[#This Row],[Credit_Score]]>=550,LoanData[[#This Row],[Credit_Score]]<=649),"High Risk", AND(LoanData[[#This Row],[Credit_Score]]>=300,LoanData[[#This Row],[Credit_Score]]<=549),"Very High Risk", LoanData[[#This Row],[Credit_Score]]="Not Available","Unclassified")} -> Medium Risk | I11: =_xlfn.XLOOKUP(H11,Reference_Tables!$B$2:$B$7,Reference_Tables!$C$2:$C$7,,0,1) -> MR | J11: =INDEX(Reference_Tables!$D$11:$D$36,MATCH(LoanData[[#This Row],[Branch]],Reference_Tables!$A$11:$A$36,0)) -> Puja Chatterjee
B12: =DATEDIF(Loan_Data!K:K,Loan_Data!L:L,"D") -> 16 | C12: =DATEDIF(LoanData[[#This Row],[Approval_Date]],TODAY(),"M") -> 47 | D12: =EDATE(LoanData[[#This Row],[Approval_Date]],LoanData[[#This Row],[Loan_Term_Months]]) -> 45890 | E12: =IF(D12<TODAY(),"YES","NO") -> YES | F12: =IFERROR(LoanData[[#This Row],[EMI]]/LoanData[[#This Row],[Monthly_Income]]*100," ") -> 54.950634 | G12: {=_xlfn.IFS(F12>40, "High DTI Risk",F12>=25, "Moderate DTI",F12<25, "Low DTI")} -> High DTI Risk | H12: {=_xlfn.IFS(AND(LoanData[[#This Row],[Credit_Score]]>=750,LoanData[[#This Row],[Credit_Score]]<=900),"Low Risk", AND(LoanData[[#This Row],[Credit_Score]]>=650,LoanData[[#This Row],[Credit_Score]]<=749),"Medium Risk", AND(LoanData[[#This Row],[Credit_Score]]>=550,LoanData[[#This Row],[Credit_Score]]<=649),"High Risk", AND(LoanData[[#This Row],[Credit_Score]]>=300,LoanData[[#This Row],[Credit_Score]]<=549),"Very High Risk", LoanData[[#This Row],[Credit_Score]]="Not Available","Unclassified")} -> Very High Risk | I12: =_xlfn.XLOOKUP(H12,Reference_Tables!$B$2:$B$7,Reference_Tables!$C$2:$C$7,,0,1) -> VHR | J12: =INDEX(Reference_Tables!$D$11:$D$36,MATCH(LoanData[[#This Row],[Branch]],Reference_Tables!$A$11:$A$36,0)) -> Ananya Sharma
B13: =DATEDIF(Loan_Data!K:K,Loan_Data!L:L,"D") -> 29 | C13: =DATEDIF(LoanData[[#This Row],[Approval_Date]],TODAY(),"M") -> 37 | D13: =EDATE(LoanData[[#This Row],[Approval_Date]],LoanData[[#This Row],[Loan_Term_Months]]) -> 50591 | E13: =IF(D13<TODAY(),"YES","NO") -> NO | F13: =IFERROR(LoanData[[#This Row],[EMI]]/LoanData[[#This Row],[Monthly_Income]]*100," ") -> 56.679013 | G13: {=_xlfn.IFS(F13>40, "High DTI Risk",F13>=25, "Moderate DTI",F13<25, "Low DTI")} -> High DTI Risk | H13: {=_xlfn.IFS(AND(LoanData[[#This Row],[Credit_Score]]>=750,LoanData[[#This Row],[Credit_Score]]<=900),"Low Risk", AND(LoanData[[#This Row],[Credit_Score]]>=650,LoanData[[#This Row],[Credit_Score]]<=749),"Medium Risk", AND(LoanData[[#This Row],[Credit_Score]]>=550,LoanData[[#This Row],[Credit_Score]]<=649),"High Risk", AND(LoanData[[#This Row],[Credit_Score]]>=300,LoanData[[#This Row],[Credit_Score]]<=549),"Very High Risk", LoanData[[#This Row],[Credit_Score]]="Not Available","Unclassified")} -> Low Risk | I13: =_xlfn.XLOOKUP(H13,Reference_Tables!$B$2:$B$7,Reference_Tables!$C$2:$C$7,,0,1) -> LR | J13: =INDEX(Reference_Tables!$D$11:$D$36,MATCH(LoanData[[#This Row],[Branch]],Reference_Tables!$A$11:$A$36,0)) -> Deepak Nair
B14: =DATEDIF(Loan_Data!K:K,Loan_Data!L:L,"D") -> 8 | C14: =DATEDIF(LoanData[[#This Row],[Approval_Date]],TODAY(),"M") -> 42 | D14: =EDATE(LoanData[[#This Row],[Approval_Date]],LoanData[[#This Row],[Loan_Term_Months]]) -> 45338 | E14: =IF(D14<TODAY(),"YES","NO") -> YES | F14: =IFERROR(LoanData[[#This Row],[EMI]]/LoanData[[#This Row],[Monthly_Income]]*100," ") -> 517.13714 | G14: {=_xlfn.IFS(F14>40, "High DTI Risk",F14>=25, "Moderate DTI",F14<25, "Low DTI")} -> High DTI Risk | H14: {=_xlfn.IFS(AND(LoanData[[#This Row],[Credit_Score]]>=750,LoanData[[#This Row],[Credit_Score]]<=900),"Low Risk", AND(LoanData[[#This Row],[Credit_Score]]>=650,LoanData[[#This Row],[Credit_Score]]<=749),"Medium Risk", AND(LoanData[[#This Row],[Credit_Score]]>=550,LoanData[[#This Row],[Credit_Score]]<=649),"High Risk", AND(LoanData[[#This Row],[Credit_Score]]>=300,LoanData[[#This Row],[Credit_Score]]<=549),"Very High Risk", LoanData[[#This Row],[Credit_Score]]="Not Available","Unclassified")} -> High Risk | I14: =_xlfn.XLOOKUP(H14,Reference_Tables!$B$2:$B$7,Reference_Tables!$C$2:$C$7,,0,1) -> HR | J14: =INDEX(Reference_Tables!$D$11:$D$36,MATCH(LoanData[[#This Row],[Branch]],Reference_Tables!$A$11:$A$36,0)) -> Ananya Sharma
B15: =DATEDIF(Loan_Data!K:K,Loan_Data!L:L,"D") -> 3 | C15: =DATEDIF(LoanData[[#This Row],[Approval_Date]],TODAY(),"M") -> 53 | D15: =EDATE(LoanData[[#This Row],[Approval_Date]],LoanData[[#This Row],[Loan_Term_Months]]) -> 44980 | E15: =IF(D15<TODAY(),"YES","NO") -> YES | F15: =IFERROR(LoanData[[#This Row],[EMI]]/LoanData[[#This Row],[Monthly_Income]]*100," ") -> 289.52178 | G15: {=_xlfn.IFS(F15>40, "High DTI Risk",F15>=25, "Moderate DTI",F15<25, "Low DTI")} -> High DTI Risk | H15: {=_xlfn.IFS(AND(LoanData[[#This Row],[Credit_Score]]>=750,LoanData[[#This Row],[Credit_Score]]<=900),"Low Risk", AND(LoanData[[#This Row],[Credit_Score]]>=650,LoanData[[#This Row],[Credit_Score]]<=749),"Medium Risk", AND(LoanData[[#This Row],[Credit_Score]]>=550,LoanData[[#This Row],[Credit_Score]]<=649),"High Risk", AND(LoanData[[#This Row],[Credit_Score]]>=300,LoanData[[#This Row],[Credit_Score]]<=549),"Very High Risk", LoanData[[#This Row],[Credit_Score]]="Not Available","Unclassified")} -> Low Risk | I15: =_xlfn.XLOOKUP(H15,Reference_Tables!$B$2:$B$7,Reference_Tables!$C$2:$C$7,,0,1) -> LR | J15: =INDEX(Reference_Tables!$D$11:$D$36,MATCH(LoanData[[#This Row],[Branch]],Reference_Tables!$A$11:$A$36,0)) -> Puja Chatterjee
... B1201: =DATEDIF(Loan_Data!K:K,Loan_Data!L:L,"D") -> 17 | C1201: =DATEDIF(LoanData[[#This Row],[Approval_Date]],TODAY(),"M") -> 59 | D1201: =EDATE(LoanData[[#This Row],[Approval_Date]],LoanData[[#This Row],[Loan_Term_Months]]) -> 48107 | E1201: =IF(D1201<TODAY(),"YES","NO") -> NO | F1201: =IFERROR(LoanData[[#This Row],[EMI]]/LoanData[[#This Row],[Monthly_Income]]*100," ") -> 0.52784372 | G1201: {=_xlfn.IFS(F1201>40, "High DTI Risk",F1201>=25, "Moderate DTI",F1201<25, "Low DTI")} -> Low DTI | H1201: {=_xlfn.IFS(AND(LoanData[[#This Row],[Credit_Score]]>=750,LoanData[[#This Row],[Credit_Score]]<=900),"Low Risk", AND(LoanData[[#This Row],[Credit_Score]]>=650,LoanData[[#This Row],[Credit_Score]]<=749),"Medium Risk", AND(LoanData[[#This Row],[Credit_Score]]>=550,LoanData[[#This Row],[Credit_Score]]<=649),"High Risk", AND(LoanData[[#This Row],[Credit_Score]]>=300,LoanData[[#This Row],[Credit_Score]]<=549),"Very High Risk", LoanData[[#This Row],[Credit_Score]]="Not Available","Unclassified")} -> Low Risk | I1201: =_xlfn.XLOOKUP(H1201,Reference_Tables!$B$2:$B$7,Reference_Tables!$C$2:$C$7,,0,1) -> LR | J1201: =INDEX(Reference_Tables!$D$11:$D$36,MATCH(LoanData[[#This Row],[Branch]],Reference_Tables!$A$11:$A$36,0)) -> Kavita Joshi

Sheet Pivot_Analysis
B2: 20. Loan Exposure by Region: Total Loan_Amount and Outstanding_Balance per Region. Which region has the highest total exposure?
H3: West
B5: Region | C5: Sum of Loan_Amount | D5: Sum of Outstanding_Balance
B6: Central | C6: 123625000 | D6: 49514738
B7: East | C7: 139425000 | D7: 51660457
B8: North | C8: 137400000 | D8: 55554824
B9: South | C9: 145300000 | D9: 54658363
B10: West | C10: 148725000 | D10: 55853474
B11: Grand Total | C11: 694475000 | D11: 2.6724186e+08
B13: 21. Risk Distribution: Count of loans and total Loan_Amount by Risk_Category. What percentage of the portfolio is High Risk or Very High Risk?
B15: Risk Distribution | C15: Count of Loan_ID | D15: Sum of Loan_Amount | H15: Loan_ID | I15: Loan_Amount
B16: High Risk | C16: 199 | D16: 0.15425321 | G16: High Risk | H16: 0.16583333 | I16: 0.15425321
B17: Low Risk | C17: 295 | D17: 0.25382483 | G17: Very High Risk | H17: 0.4025 | I17: 0.40530617
B18: Medium Risk | C18: 193 | D18: 0.15342525
B19: Unclassified | C19: 30 | D19: 0.03319054
B20: Very High Risk | C20: 483 | D20: 0.40530617
B21: Grand Total | C21: 1200 | D21: 1
B23: 22. Repayment by Employment Type: Cross-tab of Employment_Type vs Repayment_Status with Count of Loan_ID as values. Which employment type has the most defaults?
K24: Business Owner
B25: Count of Loan_ID | C25: Repayment_Status | K25: Government Employee
B26: Emplyoment_Type | C26: Closed | D26: Defaulted | E26: Grace Period | F26: Late | G26: On Track | H26: (blank) | I26: Grand Total | K26: Self-Employed
B27: Self-Employed | G27: 2 | I27: 2
B28: Business Owner | C28: 34 | D28: 25 | E28: 9 | F28: 60 | G28: 114 | I28: 242
B29: Freelancer | C29: 38 | D29: 18 | E29: 10 | F29: 55 | G29: 128 | H29: 2 | I29: 251
B30: Government Employee | C30: 28 | D30: 25 | E30: 7 | F30: 49 | G30: 135 | I30: 244
B31: Salaried | C31: 22 | D31: 19 | E31: 6 | F31: 58 | G31: 118 | I31: 223
B32: Salaried | G32: 1 | I32: 1
B33: Self-Employed | C33: 31 | D33: 25 | E33: 11 | F33: 55 | G33: 112 | H33: 3 | I33: 237
B34: Grand Total | C34: 153 | D34: 112 | E34: 43 | F34: 277 | G34: 610 | H34: 5 | I34: 1200
B36: 23. Branch Drill-Down: Nest Branch under Region in the rows. Collapse all regions and expand one at a time. Double-click a branch total to see the underlying detail — this is pivot drill-down.
B38: Branch Drill-Down
B39: Central
B40: Bhopal-Mp Nagar
B41: Indore-Main
B42: Lucknow-Hazratganj
B43: Nagpur-Dharampeth
B44: Raipur-Main
B45: East
B46: North
B47: South
B48: West
... B52: 24. Monthly Trend: Use Application_Date in rows and group it by Month and Year. Show Count of Loan_ID and Sum of Loan_Amount. Filter to Approved loans only. Which month had the highest approvals?
O53: May
B55: Loan_Status | C55: Approved
B57: Application_Date | C57: Count of Loan_ID | D57: Sum of Loan_Amount
B58: Jan | C58: 71 | D58: 43300000
B59: Feb | C59: 72 | D59: 36100000
B60: Mar | C60: 59 | D60: 32325000
B61: Apr | C61: 68 | D61: 45075000
B62: May | C62: 87 | D62: 45050000
B63: Jun | C63: 63 | D63: 36000000
B64: Jul | C64: 70 | D64: 44575000
B65: Aug | C65: 85 | D65: 64800000
B66: Sep | C66: 60 | D66: 38275000
B67: Oct | C67: 73 | D67: 42550000
B68: Nov | C68: 75 | D68: 49200000
B69: Dec | C69: 78 | D69: 42200000
B70: Grand Total | C70: 861 | D70: 519450000

Sheet Charts
B2: 25. From the Region pivot — a Clustered Column chart showing total loan amount by region.
B4: Region | C4: Sum of Loan_Amount
B5: Central | C5: 123625000
B6: East | C6: 139425000
B7: North | C7: 137400000
B8: South | C8: 145300000
B9: West | C9: 148725000
B10: Grand Total | C10: 694475000
B18: 26. From the Branch pivot — a horizontal Bar chart showing the top 10 branches by loan exposure.
B20: Branch | C20: Sum of Loan_Amount
B21: Ahmedabad-Cg Road | C21: 32825000
B22: Bangalore-Koramangala | C22: 34975000
B23: Bangalore-Whitefield | C23: 31850000
B24: Chandigarh-Main | C24: 32975000
B25: Gurgaon-Cybercity | C25: 29350000
B26: Hyderabad-Hitech | C26: 33025000
B27: Kolkata-Salt Lake | C27: 42325000
B28: Patna-Boring Road | C28: 33125000
B29: Pune-Shivajinagar | C29: 38800000
B30: Raipur-Main | C30: 30025000
B31: Grand Total | C31: 339275000
B36: 27. From the Monthly Trend pivot — a Line chart with markers showing how application volumes have moved month by month.
B56: 28. From the Risk Distribution pivot — a Pie or Doughnut chart showing the percentage split by risk category.
B58: Risk Category | C58: Sum of Loan_Amount
B59: High Risk | C59: 0.15425321
B60: Low Risk | C60: 0.25382483
B61: Medium Risk | C61: 0.15342525
B62: Unclassified | C62: 0.03319054
B63: Very High Risk | C63: 0.40530617
B64: Grand Total | C64: 1
B74: 29. Chart Decision: You need to show Repayment Status by Region to management. Would you use a Clustered Column chart or a Stacked Bar chart? Build both, then write 2–3 sentences explaining which one you chose and why. There is no single right answer — the reasoning matters.
B76: Count of Loan_ID | C76: Repayment Status
B77: Region | C77: Closed | D77: Defaulted | E77: Grace Period | F77: Late | G77: On Track | H77: (blank) | I77: Grand Total
B78: Central | C78: 29 | D78: 18 | E78: 14 | F78: 53 | G78: 113 | H78: 2 | I78: 229
B79: East | C79: 33 | D79: 19 | E79: 4 | F79: 56 | G79: 139 | I79: 251
B80: North | C80: 25 | D80: 24 | E80: 6 | F80: 50 | G80: 107 | H80: 2 | I80: 214
B81: South | C81: 38 | D81: 21 | E81: 9 | F81: 63 | G81: 120 | H81: 1 | I81: 252
B82: West | C82: 28 | D82: 30 | E82: 10 | F82: 55 | G82: 131 | I82: 254
B83: Grand Total | C83: 153 | D83: 112 | E83: 43 | F83: 277 | G83: 610 | H83: 5 | I83: 1200
B93: I would choose the Stacked Bar Chart because management often wants to see both the total exposure per region and the repayment mix inside that exposure.
B94: The stacked format makes it easy to spot regions with high default proportions while still showing overall loan volumes.

Sheet Dashboard_Shell
B1: FinServe Lending Co. – Loan Portfolio Dashboard
B3: [ Pivot Chart 1: Loan Amount by Region ] | J3: [ Slicer: Region ]
B10: [ Pivot Chart 2: Risk Segmentation ] | J10: [ Slicer: Employment Type ]
B17: [ Pivot Chart 3: Repayment Status by Branch ] | J17: [ Timeline: Application_Date ]
